Workbook
Name Slicer_Cancer_History1: #N/A
Name Slicer_City_Tier: #N/A

Sheet Cleaned - Customer Names 
A1: Customer ID | B1: Title | C1: First Name | D1: Last Name
A2: Id1 | B2: Ms | C2: Kelly | D2: Hawks
A3: Id2 | B3: Mr | C3: Matthew D | D3: Lehner
A4: Id3 | B4: Mr | C4: Phil | D4: Lu
A5: Id4 | B5: Ms | C5: Kelsey | D5: Osborne
A6: Id5 | B6: Ms | C6: Kristyn | D6: Kadala
A7: Id6 | B7: Mr | C7: Russell B. | D7: Baker
A8: Id7 | B8: Mr | C8: Scott | D8: Macpherson
A9: Id8 | B9: Mr | C9: Stephen | D9: Hallman
A10: Id9 | B10: Mr | C10: Patrick R. | D10: Moran
A11: Id10 | B11: Ms | C11: Brooke N. | D11: Benner
A12: Id11 | B12: Ms | C12: Paola Andrea | D12: Fierro Vargas
... A2336: Id2335 | B2336: Mr | C2336: Aaron K | D2336: German

Sheet Cleaned - Medical Examinations
A1: Customer ID | B1: BMI | C1: HBA1C | D1: Heart Issues | E1: Any Transplants | F1: Cancer history | G1: NumberOfMajorSurgeries | H1: Smoker | I1: Weight Status | J1: Mode Of Smoker
A2: Id1 | B2: 47.41 | C2: 7.47 | D2: No | E2: No | F2: No | G2: 0 | H2: Yes | I2: =IF(B2<18.5,"Underweight", IF(B2<=24.9,"Normal Weight", IF(B2<=29.9,"Overweight", "Obesity"))) -> Obesity | J2: {=INDEX(H2:H2336,MODE(MATCH(H2:H2336,H2:H2336,0)))} -> No
A3: Id2 | B3: 30.36 | C3: 5.77 | D3: No | E3: No | F3: No | G3: 0 | H3: Yes | I3: =IF(B3<18.5,"Underweight", IF(B3<=24.9,"Normal Weight", IF(B3<=29.9,"Overweight", "Obesity"))) -> Obesity
A4: Id3 | B4: 34.485 | C4: 11.87 | D4: Yes | E4: No | F4: No | G4: 2 | H4: Yes | I4: =IF(B4<18.5,"Underweight", IF(B4<=24.9,"Normal Weight", IF(B4<=29.9,"Overweight", "Obesity"))) -> Obesity
A5: Id4 | B5: 38.095 | C5: 6.05 | D5: No | E5: No | F5: No | G5: 0 | H5: Yes | I5: =IF(B5<18.5,"Underweight", IF(B5<=24.9,"Normal Weight", IF(B5<=29.9,"Overweight", "Obesity"))) -> Obesity
A6: Id5 | B6: 35.53 | C6: 5.45 | D6: No | E6: No | F6: No | G6: 0 | H6: Yes | I6: =IF(B6<18.5,"Underweight", IF(B6<=24.9,"Normal Weight", IF(B6<=29.9,"Overweight", "Obesity"))) -> Obesity
A7: Id6 | B7: 32.8 | C7: 6.59 | D7: No | E7: No | F7: No | G7: 0 | H7: Yes | I7: =IF(B7<18.5,"Underweight", IF(B7<=24.9,"Normal Weight", IF(B7<=29.9,"Overweight", "Obesity"))) -> Obesity
A8: Id7 | B8: 36.4 | C8: 6.07 | D8: No | E8: No | F8: No | G8: 0 | H8: Yes | I8: =IF(B8<18.5,"Underweight", IF(B8<=24.9,"Normal Weight", IF(B8<=29.9,"Overweight", "Obesity"))) -> Obesity
A9: Id8 | B9: 36.96 | C9: 7.93 | D9: No | E9: No | F9: No | G9: 3 | H9: Yes | I9: =IF(B9<18.5,"Underweight", IF(B9<=24.9,"Normal Weight", IF(B9<=29.9,"Overweight", "Obesity"))) -> Obesity
A10: Id9 | B10: 41.14 | C10: 9.58 | D10: Yes | E10: No | F10: Yes | G10: 1 | H10: Yes | I10: =IF(B10<18.5,"Underweight", IF(B10<=24.9,"Normal Weight", IF(B10<=29.9,"Overweight", "Obesity"))) -> Obesity
A11: Id10 | B11: 38.06 | C11: 10.79 | D11: No | E11: No | F11: No | G11: 0 | H11: Yes | I11: =IF(B11<18.5,"Underweight", IF(B11<=24.9,"Normal Weight", IF(B11<=29.9,"Overweight", "Obesity"))) -> Obesity
A12: Id11 | B12: 37.7 | C12: 5.96 | D12: Yes | E12: No | F12: No | G12: 2 | H12: Yes | I12: =IF(B12<18.5,"Underweight", IF(B12<=24.9,"Normal Weight", IF(B12<=29.9,"Overweight", "Obesity"))) -> Obesity
A13: Id12 | B13: 42.13 | C13: 11.9 | D13: No | E13: No | F13: No | G13: 0 | H13: Yes | I13: =IF(B13<18.5,"Underweight", IF(B13<=24.9,"Normal Weight", IF(B13<=29.9,"Overweight", "Obesity"))) -> Obesity
A14: Id13 | B14: 40.92 | C14: 8.41 | D14: No | E14: No | F14: No | G14: 0 | H14: Yes | I14: =IF(B14<18.5,"Underweight", IF(B14<=24.9,"Normal Weight", IF(B14<=29.9,"Overweight", "Obesity"))) -> Obesity
... A2336: Id2335 | B2336: 17.58 | C2336: 4.51 | D2336: No | E2336: No | F2336: No | G2336: 1 | H2336: No | I2336: =IF(B2336<18.5,"Underweight", IF(B2336<=24.9,"Normal Weight", IF(B2336<=29.9,"Overweight", "Obesity"))) -> Underweight

Sheet Cleaned - Hospitalisation Detai
A1: Customer ID | B1: Year | C1: Month | D1: Date | E1: Children | F1: Charges | G1: Hospital Tier | H1: City Tier | I1: State ID | J1: Date of Birth | K1: Age | L1: Year Average | M1: Mode of Month | N1: Mode of Hospital Tier | O1: Mode of City Tier
A2: Id2335 | B2: 1992 | C2: Jul | D2: 9 | E2: 0 | F2: 563.84 | G2: tier - 2 | H2: tier - 3 | I2: R1013 | J2: =DATE(B2,MONTH(DATEVALUE(C2&" 1")),D2) -> 33794 | K2: =DATEDIF(J2,DATE(2023,6,8),"Y") -> 30 | L2: =ROUND(AVERAGE(B2:B2344),0) -> 1983 | M2: {=INDEX(C2:C2344,MODE(MATCH(C2:C2344,C2:C2344,0)))} -> Sep | N2: {=INDEX(G2:G2344,MODE(MATCH(G2:G2344,G2:G2344,0)))} -> tier - 2 | O2: {=INDEX(H2:H2344,MODE(MATCH(H2:H2344,H2:H2344,0)))} -> tier - 2
A3: Id2334 | B3: 1992 | C3: Nov | D3: 30 | E3: 0 | F3: 570.62 | G3: tier - 2 | H3: tier - 1 | I3: R1013 | J3: =DATE(B3,MONTH(DATEVALUE(C3&" 1")),D3) -> 33938 | K3: =DATEDIF(J3,DATE(2023,6,8),"Y") -> 30
A4: Id2333 | B4: 1993 | C4: Jun | D4: 30 | E4: 0 | F4: 600 | G4: tier - 2 | H4: tier - 1 | I4: R1013 | J4: =DATE(B4,MONTH(DATEVALUE(C4&" 1")),D4) -> 34150 | K4: =DATEDIF(J4,DATE(2023,6,8),"Y") -> 29
A5: Id2332 | B5: 1992 | C5: Sep | D5: 13 | E5: 0 | F5: 604.54 | G5: tier - 3 | H5: tier - 3 | I5: R1013 | J5: =DATE(B5,MONTH(DATEVALUE(C5&" 1")),D5) -> 33860 | K5: =DATEDIF(J5,DATE(2023,6,8),"Y") -> 30
A6: Id2331 | B6: 1998 | C6: Jul | D6: 27 | E6: 0 | F6: 637.26 | G6: tier - 3 | H6: tier - 3 | I6: R1013 | J6: =DATE(B6,MONTH(DATEVALUE(C6&" 1")),D6) -> 36003 | K6: =DATEDIF(J6,DATE(2023,6,8),"Y") -> 24
A7: Id2330 | B7: 2001 | C7: Nov | D7: 20 | E7: 0 | F7: 646.14 | G7: tier - 3 | H7: tier - 3 | I7: R1012 | J7: =DATE(B7,MONTH(DATEVALUE(C7&" 1")),D7) -> 37215 | K7: =DATEDIF(J7,DATE(2023,6,8),"Y") -> 21
A8: Id2329 | B8: 1993 | C8: Jun | D8: 1 | E8: 0 | F8: 650 | G8: tier - 3 | H8: tier - 3 | I8: R1013 | J8: =DATE(B8,MONTH(DATEVALUE(C8&" 1")),D8) -> 34121 | K8: =DATEDIF(J8,DATE(2023,6,8),"Y") -> 30
A9: Id2328 | B9: 1995 | C9: Jul | D9: 4 | E9: 0 | F9: 650 | G9: tier - 3 | H9: tier - 3 | I9: R1013 | J9: =DATE(B9,MONTH(DATEVALUE(C9&" 1")),D9) -> 34884 | K9: =DATEDIF(J9,DATE(2023,6,8),"Y") -> 27
A10: Id2327 | B10: 2002 | C10: Nov | D10: 29 | E10: 0 | F10: 668 | G10: tier - 3 | H10: tier - 2 | I10: R1012 | J10: =DATE(B10,MONTH(DATEVALUE(C10&" 1")),D10) -> 37589 | K10: =DATEDIF(J10,DATE(2023,6,8),"Y") -> 20
A11: Id2326 | B11: 1997 | C11: Nov | D11: 9 | E11: 0 | F11: 670 | G11: tier - 3 | H11: tier - 3 | I11: R1013 | J11: =DATE(B11,MONTH(DATEVALUE(C11&" 1")),D11) -> 35743 | K11: =DATEDIF(J11,DATE(2023,6,8),"Y") -> 25
A12: Id2325 | B12: 2001 | C12: Sep | D12: 12 | E12: 0 | F12: 687.54 | G12: tier - 3 | H12: tier - 2 | I12: R1013 | J12: =DATE(B12,MONTH(DATEVALUE(C12&" 1")),D12) -> 37146 | K12: =DATEDIF(J12,DATE(2023,6,8),"Y") -> 21
A13: Id2324 | B13: 1999 | C13: Dec | D13: 26 | E13: 0 | F13: 700 | G13: tier - 2 | H13: tier - 3 | I13: R1013 | J13: =DATE(B13,MONTH(DATEVALUE(C13&" 1")),D13) -> 36520 | K13: =DATEDIF(J13,DATE(2023,6,8),"Y") -> 23
A14: Id2323 | B14: 1999 | C14: Dec | D14: 14 | E14: 0 | F14: 722.99 | G14: tier - 3 | H14: tier - 1 | I14: R1013 | J14: =DATE(B14,MONTH(DATEVALUE(C14&" 1")),D14) -> 36508 | K14: =DATEDIF(J14,DATE(2023,6,8),"Y") -> 23
... A46: Id2291 | B46: 2002 | C46: Aug | D46: 11 | E46: 0 | F46: 1137 | G46: tier - 3 | H46: tier - 1 | I46: R1013 | J46: =DATE(B46,MONTH(DATEVALUE(C46&" 1")),D46) -> 37479 | K46: =DATEDIF(J46,DATE(2023,6,8),"Y") -> 20
A47: Unknown | B47: 2004 | C47: Nov | D47: 6 | E47: 0 | F47: 1137.01 | G47: tier - 3 | H47: tier - 1 | I47: R1013 | J47: =DATE(B47,MONTH(DATEVALUE(C47&" 1")),D47) -> 38297 | K47: =DATEDIF(J47,DATE(2023,6,8),"Y") -> 18 | L47: Id2294 | M47: Id2294
A48: Id2290 | B48: 2004 | C48: Oct | D48: 15 | E48: 0 | F48: 1137.01 | G48: tier - 3 | H48: tier - 1 | I48: R1013 | J48: =DATE(B48,MONTH(DATEVALUE(C48&" 1")),D48) -> 38275 | K48: =DATEDIF(J48,DATE(2023,6,8),"Y") -> 18
A49: Id2289 | B49: 2004 | C49: Nov | D49: 27 | E49: 0 | F49: 1137.47 | G49: tier - 3 | H49: tier - 2 | I49: R1013 | J49: =DATE(B49,MONTH(DATEVALUE(C49&" 1")),D49) -> 38318 | K49: =DATEDIF(J49,DATE(2023,6,8),"Y") -> 18
A50: Id2288 | B50: 2001 | C50: Oct | D50: 25 | E50: 0 | F50: 1141 | G50: tier - 3 | H50: tier - 1 | I50: R1013 | J50: =DATE(B50,MONTH(DATEVALUE(C50&" 1")),D50) -> 37189 | K50: =DATEDIF(J50,DATE(2023,6,8),"Y") -> 21
A51: Id2287 | B51: 2004 | C51: Sep | D51: 12 | E51: 0 | F51: 1141.45 | G51: tier - 3 | H51: tier - 3 | I51: R1013 | J51: =DATE(B51,MONTH(DATEVALUE(C51&" 1")),D51) -> 38242 | K51: =DATEDIF(J51,DATE(2023,6,8),"Y") -> 18
A52: Id2286 | B52: 2002 | C52: Oct | D52: 1 | E52: 0 | F52: 1142 | G52: tier - 3 | H52: tier - 2 | I52: R1011 | J52: =DATE(B52,MONTH(DATEVALUE(C52&" 1")),D52) -> 37530 | K52: =DATEDIF(J52,DATE(2023,6,8),"Y") -> 20
A53: Id2285 | B53: 2004 | C53: Jun | D53: 10 | E53: 0 | F53: 1146.8 | G53: tier - 2 | H53: tier - 2 | I53: R1013 | J53: =DATE(B53,MONTH(DATEVALUE(C53&" 1")),D53) -> 38148 | K53: =DATEDIF(J53,DATE(2023,6,8),"Y") -> 18
A54: Id2284 | B54: 2003 | C54: Jun | D54: 12 | E54: 0 | F54: 1149 | G54: tier - 2 | H54: tier - 1 | I54: R1012 | J54: =DATE(B54,MONTH(DATEVALUE(C54&" 1")),D54) -> 37784 | K54: =DATEDIF(J54,DATE(2023,6,8),"Y") -> 19
A55: Id2283 | B55: 2004 | C55: Jul | D55: 18 | E55: 0 | F55: 1149.4 | G55: tier - 2 | H55: tier - 2 | I55: R1013 | J55: =DATE(B55,MONTH(DATEVALUE(C55&" 1")),D55) -> 38186 | K55: =DATEDIF(J55,DATE(2023,6,8),"Y") -> 18
A56: Id2282 | B56: 1994 | C56: Jul | D56: 26 | E56: 0 | F56: 1158.32 | G56: tier - 2 | H56: tier - 1 | I56: R1013 | J56: =DATE(B56,MONTH(DATEVALUE(C56&" 1")),D56) -> 34541 | K56: =DATEDIF(J56,DATE(2023,6,8),"Y") -> 28
A57: Id2281 | B57: 2004 | C57: Nov | D57: 11 | E57: 0 | F57: 1163.46 | G57: tier - 2 | H57: tier - 3 | I57: R1013 | J57: =DATE(B57,MONTH(DATEVALUE(C57&" 1")),D57) -> 38302 | K57: =DATEDIF(J57,DATE(2023,6,8),"Y") -> 18
A58: Id2280 | B58: 2002 | C58: Jun | D58: 11 | E58: 0 | F58: 1165 | G58: tier - 2 | H58: tier - 3 | I58: R1012 | J58: =DATE(B58,MONTH(DATEVALUE(C58&" 1")),D58) -> 37418 | K58: =DATEDIF(J58,DATE(2023,6,8),"Y") -> 20
A59: Id2279 | B59: 2001 | C59: Nov | D59: 12 | E59: 0 | F59: 1167 | G59: tier - 2 | H59: tier - 1 | I59: R1013 | J59: =DATE(B59,MONTH(DATEVALUE(C59&" 1")),D59) -> 37207 | K59: =DATEDIF(J59,DATE(2023,6,8),"Y") -> 21
... A295: Id2043 | B295: 2004 | C295: Nov | D295: 14 | E295: 0 | F295: 2773.46 | G295: tier - 2 | H295: tier - 1 | I295: R1021 | J295: =DATE(B295,MONTH(DATEVALUE(C295&" 1")),D295) -> 38305 | K295: =DATEDIF(J295,DATE(2023,6,8),"Y") -> 18
A296: Unknown | B296: 1999 | C296: Jun | D296: 9 | E296: 1 | F296: 2775.19 | G296: tier - 2 | H296: tier - 1 | I296: R1012 | J296: =DATE(B296,MONTH(DATEVALUE(C296&" 1")),D296) -> 36320 | K296: =DATEDIF(J296,DATE(2023,6,8),"Y") -> 23 | L296: Id2045 | M296: Id2045
A297: Id2042 | B297: 1999 | C297: Aug | D297: 29 | E297: 1 | F297: 2775.19 | G297: tier - 2 | H297: tier - 1 | I297: R1012 | J297: =DATE(B297,MONTH(DATEVALUE(C297&" 1")),D297) -> 36401 | K297: =DATEDIF(J297,DATE(2023,6,8),"Y") -> 23
A298: Id2041 | B298: 1999 | C298: Dec | D298: 24 | E298: 1 | F298: 2789.06 | G298: tier - 2 | H298: tier - 3 | I298: R1012 | J298: =DATE(B298,MONTH(DATEVALUE(C298&" 1")),D298) -> 36518 | K298: =DATEDIF(J298,DATE(2023,6,8),"Y") -> 23
A299: Id2040 | B299: 2004 | C299: Aug | D299: 4 | E299: 2 | F299: 2801.26 | G299: tier - 2 | H299: tier - 3 | I299: R1013 | J299: =DATE(B299,MONTH(DATEVALUE(C299&" 1")),D299) -> 38203 | K299: =DATEDIF(J299,DATE(2023,6,8),"Y") -> 18
A300: Id2039 | B300: 2003 | C300: Sep | D300: 23 | E300: 2 | F300: 2803.7 | G300: tier - 2 | H300: tier - 1 | I300: R1012 | J300: =DATE(B300,MONTH(DATEVALUE(C300&" 1")),D300) -> 37887 | K300: =DATEDIF(J300,DATE(2023,6,8),"Y") -> 19
A301: Id2038 | B301: 2000 | C301: Oct | D301: 1 | E301: 0 | F301: 2819.51 | G301: tier - 2 | H301: tier - 3 | I301: R1011 | J301: =DATE(B301,MONTH(DATEVALUE(C301&" 1")),D301) -> 36800 | K301: =DATEDIF(J301,DATE(2023,6,8),"Y") -> 22
A302: Id2037 | B302: 1998 | C302: Nov | D302: 15 | E302: 0 | F302: 2842.76 | G302: tier - 2 | H302: tier - 3 | I302: R1012 | J302: =DATE(B302,MONTH(DATEVALUE(C302&" 1")),D302) -> 36114 | K302: =DATEDIF(J302,DATE(2023,6,8),"Y") -> 24
A303: Id2036 | B303: 1998 | C303: Jun | D303: 17 | E303: 0 | F303: 2850.68 | G303: tier - 2 | H303: tier - 3 | I303: R1012 | J303: =DATE(B303,MONTH(DATEVALUE(C303&" 1")),D303) -> 35963 | K303: =DATEDIF(J303,DATE(2023,6,8),"Y") -> 24
A304: Id2035 | B304: 1998 | C304: Sep | D304: 4 | E304: 0 | F304: 2855.44 | G304: tier - 2 | H304: tier - 3 | I304: R1012 | J304: =DATE(B304,MONTH(DATEVALUE(C304&" 1")),D304) -> 36042 | K304: =DATEDIF(J304,DATE(2023,6,8),"Y") -> 24
A305: Id2034 | B305: 1993 | C305: Nov | D305: 1 | E305: 0 | F305: 2866.09 | G305: tier - 3 | H305: tier - 3 | I305: R1011 | J305: =DATE(B305,MONTH(DATEVALUE(C305&" 1")),D305) -> 34274 | K305: =DATEDIF(J305,DATE(2023,6,8),"Y") -> 29
A306: Id2033 | B306: 1993 | C306: Aug | D306: 12 | E306: 0 | F306: 2867.12 | G306: tier - 1 | H306: tier - 3 | I306: R1013 | J306: =DATE(B306,MONTH(DATEVALUE(C306&" 1")),D306) -> 34193 | K306: =DATEDIF(J306,DATE(2023,6,8),"Y") -> 29
A307: Id2032 | B307: 1996 | C307: Jun | D307: 21 | E307: 0 | F307: 2897.32 | G307: tier - 3 | H307: tier - 3 | I307: R1016 | J307: =DATE(B307,MONTH(DATEVALUE(C307&" 1")),D307) -> 35237 | K307: =DATEDIF(J307,DATE(2023,6,8),"Y") -> 26
A308: Id2031 | B308: 2000 | C308: Jul | D308: 14 | E308: 0 | F308: 2897.46 | G308: tier - 2 | H308: tier - 1 | I308: R1012 | J308: =DATE(B308,MONTH(DATEVALUE(C308&" 1")),D308) -> 36721 | K308: =DATEDIF(J308,DATE(2023,6,8),"Y") -> 22
... A732: Id1607 | B732: 1985 | C732: Jul | D732: 22 | E732: 2 | F732: 6198.75 | G732: tier - 2 | H732: tier - 1 | I732: R1012 | J732: =DATE(B732,MONTH(DATEVALUE(C732&" 1")),D732) -> 31250 | K732: =DATEDIF(J732,DATE(2023,6,8),"Y") -> 37
A733: Unknown | B733: 1985 | C733: Dec | D733: 20 | E733: 2 | F733: 6203.9 | G733: tier - 1 | H733: tier - 2 | I733: R1012 | J733: =DATE(B733,MONTH(DATEVALUE(C733&" 1")),D733) -> 31401 | K733: =DATEDIF(J733,DATE(2023,6,8),"Y") -> 37 | L733: Id1608 | M733: Id1608
A734: Id1606 | B734: 1985 | C734: Sep | D734: 22 | E734: 2 | F734: 6203.9 | G734: tier - 2 | H734: tier - 2 | I734: R1012 | J734: =DATE(B734,MONTH(DATEVALUE(C734&" 1")),D734) -> 31312 | K734: =DATEDIF(J734,DATE(2023,6,8),"Y") -> 37
A735: Id1605 | B735: 1999 | C735: Sep | D735: 10 | E735: 0 | F735: 6207.26 | G735: tier - 2 | H735: tier - 2 | I735: R1026 | J735: =DATE(B735,MONTH(DATEVALUE(C735&" 1")),D735) -> 36413 | K735: =DATEDIF(J735,DATE(2023,6,8),"Y") -> 23
A736: Id1604 | B736: 1992 | C736: Aug | D736: 12 | E736: 0 | F736: 6208.5 | G736: tier - 2 | H736: tier - 1 | I736: R1021 | J736: =DATE(B736,MONTH(DATEVALUE(C736&" 1")),D736) -> 33828 | K736: =DATEDIF(J736,DATE(2023,6,8),"Y") -> 30
A737: Id1603 | B737: 1972 | C737: Jun | D737: 29 | E737: 0 | F737: 6219.93 | G737: tier - 2 | H737: tier - 2 | I737: R1013 | J737: =DATE(B737,MONTH(DATEVALUE(C737&" 1")),D737) -> 26479 | K737: =DATEDIF(J737,DATE(2023,6,8),"Y") -> 50
A738: Id1602 | B738: 1978 | C738: Sep | D738: 19 | E738: 2 | F738: 6236.95 | G738: tier - 2 | H738: tier - 2 | I738: R1013 | J738: =DATE(B738,MONTH(DATEVALUE(C738&" 1")),D738) -> 28752 | K738: =DATEDIF(J738,DATE(2023,6,8),"Y") -> 44
A739: Id1601 | B739: 1983 | C739: Aug | D739: 11 | E739: 1 | F739: 6238.3 | G739: tier - 2 | H739: tier - 1 | I739: R1011 | J739: =DATE(B739,MONTH(DATEVALUE(C739&" 1")),D739) -> 30539 | K739: =DATEDIF(J739,DATE(2023,6,8),"Y") -> 39
A740: Id1600 | B740: 1979 | C740: Oct | D740: 10 | E740: 0 | F740: 6250.44 | G740: tier - 2 | H740: tier - 1 | I740: R1011 | J740: =DATE(B740,MONTH(DATEVALUE(C740&" 1")),D740) -> 29138 | K740: =DATEDIF(J740,DATE(2023,6,8),"Y") -> 43
A741: Id1599 | B741: 1972 | C741: Nov | D741: 11 | E741: 0 | F741: 6253.85 | G741: tier - 2 | H741: tier - 2 | I741: R1013 | J741: =DATE(B741,MONTH(DATEVALUE(C741&" 1")),D741) -> 26614 | K741: =DATEDIF(J741,DATE(2023,6,8),"Y") -> 50
A742: Id1598 | B742: 1972 | C742: Sep | D742: 8 | E742: 0 | F742: 6254.13 | G742: tier - 2 | H742: tier - 2 | I742: R1012 | J742: =DATE(B742,MONTH(DATEVALUE(C742&" 1")),D742) -> 26550 | K742: =DATEDIF(J742,DATE(2023,6,8),"Y") -> 50
A743: Id1597 | B743: 1970 | C743: Oct | D743: 11 | E743: 0 | F743: 6255.38 | G743: tier - 2 | H743: tier - 2 | I743: R1013 | J743: =DATE(B743,MONTH(DATEVALUE(C743&" 1")),D743) -> 25852 | K743: =DATEDIF(J743,DATE(2023,6,8),"Y") -> 52
A744: Id1596 | B744: 1995 | C744: Oct | D744: 17 | E744: 0 | F744: 6261.2 | G744: tier - 2 | H744: tier - 1 | I744: R1026 | J744: =DATE(B744,MONTH(DATEVALUE(C744&" 1")),D744) -> 34989 | K744: =DATEDIF(J744,DATE(2023,6,8),"Y") -> 27
A745: Id1595 | B745: 1984 | C745: Sep | D745: 25 | E745: 3 | F745: 6269.33 | G745: tier - 2 | H745: tier - 1 | I745: R1013 | J745: =DATE(B745,MONTH(DATEVALUE(C745&" 1")),D745) -> 30950 | K745: =DATEDIF(J745,DATE(2023,6,8),"Y") -> 38
... A2130: Id212 | B2130: 1971 | C2130: Aug | D2130: 10 | E2130: 0 | F2130: 35583.17 | G2130: tier - 1 | H2130: tier - 3 | I2130: R1011 | J2130: =DATE(B2130,MONTH(DATEVALUE(C2130&" 1")),D2130) -> 26155 | K2130: =DATEDIF(J2130,DATE(2023,6,8),"Y") -> 51
A2131: Unknown | B2131: 2000 | C2131: Oct | D2131: 13 | E2131: 0 | F2131: 35585.58 | G2131: tier - 1 | H2131: tier - 2 | I2131: R1011 | J2131: =DATE(B2131,MONTH(DATEVALUE(C2131&" 1")),D2131) -> 36812 | K2131: =DATEDIF(J2131,DATE(2023,6,8),"Y") -> 22 | L2131: Id212 | M2131: Id212
A2132: Id211 | B2132: 2000 | C2132: Nov | D2132: 19 | E2132: 0 | F2132: 35585.58 | G2132: tier - 2 | H2132: tier - 3 | I2132: R1011 | J2132: =DATE(B2132,MONTH(DATEVALUE(C2132&" 1")),D2132) -> 36849 | K2132: =DATEDIF(J2132,DATE(2023,6,8),"Y") -> 22
A2133: Id210 | B2133: 2000 | C2133: Dec | D2133: 17 | E2133: 3 | F2133: 35595.59 | G2133: tier - 2 | H2133: tier - 3 | I2133: R1013 | J2133: =DATE(B2133,MONTH(DATEVALUE(C2133&" 1")),D2133) -> 36877 | K2133: =DATEDIF(J2133,DATE(2023,6,8),"Y") -> 22
A2134: Id209 | B2134: 1978 | C2134: Dec | D2134: 19 | E2134: 2 | F2134: 35701.9 | G2134: tier - 2 | H2134: tier - 1 | I2134: R1011 | J2134: =DATE(B2134,MONTH(DATEVALUE(C2134&" 1")),D2134) -> 28843 | K2134: =DATEDIF(J2134,DATE(2023,6,8),"Y") -> 44
A2135: Id208 | B2135: 1974 | C2135: Jul | D2135: 15 | E2135: 0 | F2135: 35711.39 | G2135: tier - 2 | H2135: tier - 3 | I2135: R1012 | J2135: =DATE(B2135,MONTH(DATEVALUE(C2135&" 1")),D2135) -> 27225 | K2135: =DATEDIF(J2135,DATE(2023,6,8),"Y") -> 48
A2136: Id207 | B2136: 1976 | C2136: Oct | D2136: 4 | E2136: 2 | F2136: 35733.96 | G2136: tier - 2 | H2136: tier - 2 | I2136: R1011 | J2136: =DATE(B2136,MONTH(DATEVALUE(C2136&" 1")),D2136) -> 28037 | K2136: =DATEDIF(J2136,DATE(2023,6,8),"Y") -> 46
A2137: Id206 | B2137: 1992 | C2137: Jun | D2137: 18 | E2137: 0 | F2137: 35883.27 | G2137: tier - 2 | H2137: tier - 1 | I2137: R1011 | J2137: =DATE(B2137,MONTH(DATEVALUE(C2137&" 1")),D2137) -> 33773 | K2137: =DATEDIF(J2137,DATE(2023,6,8),"Y") -> 30
A2138: Id205 | B2138: 1981 | C2138: Nov | D2138: 22 | E2138: 1 | F2138: 35952.65 | G2138: tier - 1 | H2138: tier - 3 | I2138: R1011 | J2138: =DATE(B2138,MONTH(DATEVALUE(C2138&" 1")),D2138) -> 29912 | K2138: =DATEDIF(J2138,DATE(2023,6,8),"Y") -> 41
A2139: Id204 | B2139: 1999 | C2139: Sep | D2139: 4 | E2139: 2 | F2139: 36021.01 | G2139: tier - 2 | H2139: tier - 3 | I2139: R1013 | J2139: =DATE(B2139,MONTH(DATEVALUE(C2139&" 1")),D2139) -> 36407 | K2139: =DATEDIF(J2139,DATE(2023,6,8),"Y") -> 23
A2140: Id203 | B2140: 1963 | C2140: Jul | D2140: 22 | E2140: 0 | F2140: 36074.34 | G2140: tier - 2 | H2140: tier - 1 | I2140: R1011 | J2140: =DATE(B2140,MONTH(DATEVALUE(C2140&" 1")),D2140) -> 23214 | K2140: =DATEDIF(J2140,DATE(2023,6,8),"Y") -> 59
A2141: Id202 | B2141: 1996 | C2141: Aug | D2141: 20 | E2141: 2 | F2141: 36085.22 | G2141: tier - 1 | H2141: tier - 1 | I2141: R1011 | J2141: =DATE(B2141,MONTH(DATEVALUE(C2141&" 1")),D2141) -> 35297 | K2141: =DATEDIF(J2141,DATE(2023,6,8),"Y") -> 26
A2142: Id201 | B2142: 1979 | C2142: Nov | D2142: 4 | E2142: 2 | F2142: 36090.49 | G2142: tier - 2 | H2142: tier - 2 | I2142: R1011 | J2142: =DATE(B2142,MONTH(DATEVALUE(C2142&" 1")),D2142) -> 29163 | K2142: =DATEDIF(J2142,DATE(2023,6,8),"Y") -> 43
A2143: Id200 | B2143: 1997 | C2143: Jun | D2143: 12 | E2143: 2 | F2143: 36124.57 | G2143: tier - 1 | H2143: tier - 3 | I2143: R1013 | J2143: =DATE(B2143,MONTH(DATEVALUE(C2143&" 1")),D2143) -> 35593 | K2143: =DATEDIF(J2143,DATE(2023,6,8),"Y") -> 25
... A2159: Id184 | B2159: 1965 | C2159: Dec | D2159: 28 | E2159: 0 | F2159: 36795.29 | G2159: tier - 2 | H2159: tier - 1 | I2159: R1011 | J2159: =DATE(B2159,MONTH(DATEVALUE(C2159&" 1")),D2159) -> 24104 | K2159: =DATEDIF(J2159,DATE(2023,6,8),"Y") -> 57
A2160: Unknown | B2160: 1992 | C2160: Oct | D2160: 6 | E2160: 0 | F2160: 36837.47 | G2160: tier - 1 | H2160: tier - 2 | I2160: R1011 | J2160: =DATE(B2160,MONTH(DATEVALUE(C2160&" 1")),D2160) -> 33883 | K2160: =DATEDIF(J2160,DATE(2023,6,8),"Y") -> 30 | L2160: Id183 | M2160: Id183
A2161: Id183 | B2161: 1992 | C2161: Jul | D2161: 4 | E2161: 0 | F2161: 36837.47 | G2161: tier - 2 | H2161: tier - 3 | I2161: R1011 | J2161: =DATE(B2161,MONTH(DATEVALUE(C2161&" 1")),D2161) -> 33789 | K2161: =DATEDIF(J2161,DATE(2023,6,8),"Y") -> 30
A2162: Id182 | B2162: 1972 | C2162: Dec | D2162: 5 | E2162: 0 | F2162: 36889.99 | G2162: tier - 1 | H2162: tier - 3 | I2162: R1011 | J2162: =DATE(B2162,MONTH(DATEVALUE(C2162&" 1")),D2162) -> 26638 | K2162: =DATEDIF(J2162,DATE(2023,6,8),"Y") -> 50
A2163: Id181 | B2163: 2003 | C2163: Jun | D2163: 21 | E2163: 0 | F2163: 36898.73 | G2163: tier - 2 | H2163: tier - 1 | I2163: R1012 | J2163: =DATE(B2163,MONTH(DATEVALUE(C2163&" 1")),D2163) -> 37793 | K2163: =DATEDIF(J2163,DATE(2023,6,8),"Y") -> 19
A2164: Id180 | B2164: 1963 | C2164: Jul | D2164: 24 | E2164: 2 | F2164: 36910.61 | G2164: tier - 2 | H2164: tier - 2 | I2164: R1011 | J2164: =DATE(B2164,MONTH(DATEVALUE(C2164&" 1")),D2164) -> 23216 | K2164: =DATEDIF(J2164,DATE(2023,6,8),"Y") -> 59
A2165: Id179 | B2165: 1991 | C2165: Jun | D2165: 10 | E2165: 3 | F2165: 36911.99 | G2165: tier - 2 | H2165: tier - 2 | I2165: R1011 | J2165: =DATE(B2165,MONTH(DATEVALUE(C2165&" 1")),D2165) -> 33399 | K2165: =DATEDIF(J2165,DATE(2023,6,8),"Y") -> 31
A2166: Id178 | B2166: 1968 | C2166: Oct | D2166: 22 | E2166: 0 | F2166: 36922.61 | G2166: tier - 2 | H2166: tier - 1 | I2166: R1011 | J2166: =DATE(B2166,MONTH(DATEVALUE(C2166&" 1")),D2166) -> 25133 | K2166: =DATEDIF(J2166,DATE(2023,6,8),"Y") -> 54
A2167: Id177 | B2167: 1977 | C2167: Aug | D2167: 13 | E2167: 2 | F2167: 36935.64 | G2167: tier - 2 | H2167: tier - 1 | I2167: R1011 | J2167: =DATE(B2167,MONTH(DATEVALUE(C2167&" 1")),D2167) -> 28350 | K2167: =DATEDIF(J2167,DATE(2023,6,8),"Y") -> 45
A2168: Id176 | B2168: 1992 | C2168: Aug | D2168: 25 | E2168: 0 | F2168: 36950.26 | G2168: tier - 1 | H2168: tier - 1 | I2168: R1013 | J2168: =DATE(B2168,MONTH(DATEVALUE(C2168&" 1")),D2168) -> 33841 | K2168: =DATEDIF(J2168,DATE(2023,6,8),"Y") -> 30
A2169: Id175 | B2169: 1992 | C2169: Sep | D2169: 13 | E2169: 0 | F2169: 36976.45 | G2169: tier - 2 | H2169: tier - 3 | I2169: R1011 | J2169: =DATE(B2169,MONTH(DATEVALUE(C2169&" 1")),D2169) -> 33860 | K2169: =DATEDIF(J2169,DATE(2023,6,8),"Y") -> 30
A2170: Id174 | B2170: 1991 | C2170: Nov | D2170: 1 | E2170: 3 | F2170: 37040.88 | G2170: tier - 2 | H2170: tier - 2 | I2170: R1011 | J2170: =DATE(B2170,MONTH(DATEVALUE(C2170&" 1")),D2170) -> 33543 | K2170: =DATEDIF(J2170,DATE(2023,6,8),"Y") -> 31
A2171: Id173 | B2171: 1988 | C2171: Dec | D2171: 17 | E2171: 3 | F2171: 37076.37 | G2171: tier - 2 | H2171: tier - 1 | I2171: R1011 | J2171: =DATE(B2171,MONTH(DATEVALUE(C2171&" 1")),D2171) -> 32494 | K2171: =DATEDIF(J2171,DATE(2023,6,8),"Y") -> 34
A2172: Id172 | B2172: 1989 | C2172: Jun | D2172: 10 | E2172: 0 | F2172: 37079.37 | G2172: tier - 2 | H2172: tier - 3 | I2172: R1011 | J2172: =DATE(B2172,MONTH(DATEVALUE(C2172&" 1")),D2172) -> 32669 | K2172: =DATEDIF(J2172,DATE(2023,6,8),"Y") -> 33
... A2203: Id141 | B2203: 1986 | C2203: Jul | D2203: 20 | E2203: 1 | F2203: 38709.18 | G2203: tier - 1 | H2203: tier - 3 | I2203: R1013 | J2203: =DATE(B2203,MONTH(DATEVALUE(C2203&" 1")),D2203) -> 31613 | K2203: =DATEDIF(J2203,DATE(2023,6,8),"Y") -> 36
A2204: Unknown | B2204: 1991 | C2204: Nov | D2204: 22 | E2204: 2 | F2204: 38711 | G2204: tier - 1 | H2204: tier - 3 | I2204: R1011 | J2204: =DATE(B2204,MONTH(DATEVALUE(C2204&" 1")),D2204) -> 33564 | K2204: =DATEDIF(J2204,DATE(2023,6,8),"Y") -> 31 | L2204: Id139 | M2204: Id139
A2205: Id140 | B2205: 1991 | C2205: Nov | D2205: 2 | E2205: 2 | F2205: 38711 | G2205: tier - 2 | H2205: tier - 2 | I2205: R1011 | J2205: =DATE(B2205,MONTH(DATEVALUE(C2205&" 1")),D2205) -> 33544 | K2205: =DATEDIF(J2205,DATE(2023,6,8),"Y") -> 31
A2206: Id139 | B2206: 1976 | C2206: Jun | D2206: 15 | E2206: 2 | F2206: 38740.12 | G2206: tier - 2 | H2206: tier - 2 | I2206: R1012 | J2206: =DATE(B2206,MONTH(DATEVALUE(C2206&" 1")),D2206) -> 27926 | K2206: =DATEDIF(J2206,DATE(2023,6,8),"Y") -> 46
A2207: Id138 | B2207: 1991 | C2207: Nov | D2207: 8 | E2207: 3 | F2207: 38746.36 | G2207: tier - 1 | H2207: tier - 2 | I2207: R1012 | J2207: =DATE(B2207,MONTH(DATEVALUE(C2207&" 1")),D2207) -> 33550 | K2207: =DATEDIF(J2207,DATE(2023,6,8),"Y") -> 31
A2208: Id137 | B2208: 2004 | C2208: Dec | D2208: 5 | E2208: 0 | F2208: 38792.69 | G2208: tier - 2 | H2208: tier - 2 | I2208: R1013 | J2208: =DATE(B2208,MONTH(DATEVALUE(C2208&" 1")),D2208) -> 38326 | K2208: =DATEDIF(J2208,DATE(2023,6,8),"Y") -> 18
A2209: Id136 | B2209: 1979 | C2209: Dec | D2209: 3 | E2209: 2 | F2209: 38836.98 | G2209: tier - 2 | H2209: tier - 1 | I2209: R1011 | J2209: =DATE(B2209,MONTH(DATEVALUE(C2209&" 1")),D2209) -> 29192 | K2209: =DATEDIF(J2209,DATE(2023,6,8),"Y") -> 43
A2210: Id135 | B2210: 1964 | C2210: Jun | D2210: 6 | E2210: 0 | F2210: 38869.25 | G2210: tier - 2 | H2210: tier - 2 | I2210: R1011 | J2210: =DATE(B2210,MONTH(DATEVALUE(C2210&" 1")),D2210) -> 23534 | K2210: =DATEDIF(J2210,DATE(2023,6,8),"Y") -> 59
A2211: Id134 | B2211: 1967 | C2211: Jul | D2211: 30 | E2211: 0 | F2211: 38893.36 | G2211: tier - 1 | H2211: tier - 2 | I2211: R1011 | J2211: =DATE(B2211,MONTH(DATEVALUE(C2211&" 1")),D2211) -> 24683 | K2211: =DATEDIF(J2211,DATE(2023,6,8),"Y") -> 55
A2212: Id133 | B2212: 1987 | C2212: Jun | D2212: 16 | E2212: 3 | F2212: 38924.04 | G2212: tier - 2 | H2212: tier - 2 | I2212: R1011 | J2212: =DATE(B2212,MONTH(DATEVALUE(C2212&" 1")),D2212) -> 31944 | K2212: =DATEDIF(J2212,DATE(2023,6,8),"Y") -> 35
A2213: Id132 | B2213: 1976 | C2213: Dec | D2213: 15 | E2213: 2 | F2213: 38932.56 | G2213: tier - 2 | H2213: tier - 3 | I2213: R1011 | J2213: =DATE(B2213,MONTH(DATEVALUE(C2213&" 1")),D2213) -> 28109 | K2213: =DATEDIF(J2213,DATE(2023,6,8),"Y") -> 46
A2214: Id131 | B2214: 1980 | C2214: Sep | D2214: 24 | E2214: 2 | F2214: 38947.43 | G2214: tier - 2 | H2214: tier - 3 | I2214: R1011 | J2214: =DATE(B2214,MONTH(DATEVALUE(C2214&" 1")),D2214) -> 29488 | K2214: =DATEDIF(J2214,DATE(2023,6,8),"Y") -> 42
A2215: Id130 | B2215: 1978 | C2215: Oct | D2215: 12 | E2215: 2 | F2215: 38998.55 | G2215: tier - 1 | H2215: tier - 1 | I2215: R1011 | J2215: =DATE(B2215,MONTH(DATEVALUE(C2215&" 1")),D2215) -> 28775 | K2215: =DATEDIF(J2215,DATE(2023,6,8),"Y") -> 44
A2216: Id129 | B2216: 1985 | C2216: Sep | D2216: 20 | E2216: 1 | F2216: 39047.29 | G2216: tier - 1 | H2216: tier - 3 | I2216: R1017 | J2216: =DATE(B2216,MONTH(DATEVALUE(C2216&" 1")),D2216) -> 31310 | K2216: =DATEDIF(J2216,DATE(2023,6,8),"Y") -> 37
... A2344: Id1 | B2344: 1968 | C2344: Oct | D2344: 12 | E2344: 0 | F2344: 63770.43 | G2344: tier - 1 | H2344: tier - 3 | I2344: R1013 | J2344: =DATE(B2344,MONTH(DATEVALUE(C2344&" 1")),D2344) -> 25123 | K2344: =DATEDIF(J2344,DATE(2023,6,8),"Y") -> 54
A2345: =COUNTA(A2:A2344) -> 2343
...

Sheet Healthcare
A1: Customer ID | B1: First Name | C1: BMI | D1: HBA1C | E1: Heart Issues | F1: Any Transplants | G1: Cancer History | H1: Number of Major Surgeries | I1: Smoker | J1: Weight Status | K1: Diabetes Status | L1: Date of Birth | M1: Charges | N1: Hospital Tier | O1: City Tier | P1: State ID | Q1: Age
A2: Id1 | B2: =_xlfn.XLOOKUP(A2,'Cleaned - Customer Names '!$A$2:$A$2336,'Cleaned - Customer Names '!$C$2:$C$2336,0) -> Kelly | C2: =_xlfn.XLOOKUP($A2,'Cleaned - Medical Examinations'!$A$2:$A$2336,'Cleaned - Medical Examinations'!$B$2:$B$2336,0) -> 47.41 | D2: =_xlfn.XLOOKUP($A2,'Cleaned - Medical Examinations'!$A$2:$A$2336,'Cleaned - Medical Examinations'!$C$2:$C$2336,0) -> 7.47 | E2: =_xlfn.XLOOKUP($A2,'Cleaned - Medical Examinations'!$A$2:$A$2336,'Cleaned - Medical Examinations'!$D$2:$D$2336,0) -> No | F2: =_xlfn.XLOOKUP($A2,'Cleaned - Medical Examinations'!$A$2:$A$2336,'Cleaned - Medical Examinations'!$E$2:$E$2336,0) -> No | G2: =_xlfn.XLOOKUP($A2,'Cleaned - Medical Examinations'!$A$2:$A$2336,'Cleaned - Medical Examinations'!$F$2:$F$2336,0) -> No | H2: =_xlfn.XLOOKUP($A2,'Cleaned - Medical Examinations'!$A$2:$A$2336,'Cleaned - Medical Examinations'!$G$2:$G$2336,0) -> 0 | I2: =_xlfn.XLOOKUP($A2,'Cleaned - Medical Examinations'!$A$2:$A$2336,'Cleaned - Medical Examinations'!$H$2:$H$2336,0) -> Yes | J2: =_xlfn.XLOOKUP($A2,'Cleaned - Medical Examinations'!$A$2:$A$2336,'Cleaned - Medical Examinations'!$I$2:$I$2336,0) -> Obesity | K2: =IF(D2>=6.5,"Diabetic","Non-Diabetic") -> Diabetic | L2: =_xlfn.XLOOKUP($A2,'Cleaned - Hospitalisation Detai'!$A$2:$A$2344,'Cleaned - Hospitalisation Detai'!$J$2:$J$2344,0) -> 25123 | M2: =_xlfn.XLOOKUP($A2,'Cleaned - Hospitalisation Detai'!$A$2:$A$2344,'Cleaned - Hospitalisation Detai'!$F$2:$F$2344,0) -> 63770.43 | N2: =_xlfn.XLOOKUP($A2,'Cleaned - Hospitalisation Detai'!$A$2:$A$2344,'Cleaned - Hospitalisation Detai'!$G$2:$G$2344,0) -> tier - 1 | O2: =_xlfn.XLOOKUP($A2,'Cleaned - Hospitalisation Detai'!$A$2:$A$2344,'Cleaned - Hospitalisation Detai'!$H$2:$H$2344,0) -> tier - 3 | P2: =_xlfn.XLOOKUP($A2,'Cleaned - Hospitalisation Detai'!$A$2:$A$2344,'Cleaned - Hospitalisation Detai'!$I$2:$I$2344,0) -> R1013 | Q2: =_xlfn.XLOOKUP($A2,'Cleaned - Hospitalisation Detai'!$A$2:$A$2344,'Cleaned - Hospitalisation Detai'!$K$2:$K$2344,0) -> 54
A3: Id2 | B3: =_xlfn.XLOOKUP(A3,'Cleaned - Customer Names '!$A$2:$A$2336,'Cleaned - Customer Names '!$C$2:$C$2336,0) -> Matthew D | C3: =_xlfn.XLOOKUP($A3,'Cleaned - Medical Examinations'!$A$2:$A$2336,'Cleaned - Medical Examinations'!$B$2:$B$2336,0) -> 30.36 | D3: =_xlfn.XLOOKUP($A3,'Cleaned - Medical Examinations'!$A$2:$A$2336,'Cleaned - Medical Examinations'!$C$2:$C$2336,0) -> 5.77 | E3: =_xlfn.XLOOKUP($A3,'Cleaned - Medical Examinations'!$A$2:$A$2336,'Cleaned - Medical Examinations'!$D$2:$D$2336,0) -> No | F3: =_xlfn.XLOOKUP($A3,'Cleaned - Medical Examinations'!$A$2:$A$2336,'Cleaned - Medical Examinations'!$E$2:$E$2336,0) -> No | G3: =_xlfn.XLOOKUP($A3,'Cleaned - Medical Examinations'!$A$2:$A$2336,'Cleaned - Medical Examinations'!$F$2:$F$2336,0) -> No | H3: =_xlfn.XLOOKUP($A3,'Cleaned - Medical Examinations'!$A$2:$A$2336,'Cleaned - Medical Examinations'!$G$2:$G$2336,0) -> 0 | I3: =_xlfn.XLOOKUP($A3,'Cleaned - Medical Examinations'!$A$2:$A$2336,'Cleaned - Medical Examinations'!$H$2:$H$2336,0) -> Yes | J3: =_xlfn.XLOOKUP($A3,'Cleaned - Medical Examinations'!$A$2:$A$2336,'Cleaned - Medical Examinations'!$I$2:$I$2336,0) -> Obesity | K3: =IF(D3>=6.5,"Diabetic","Non-Diabetic") -> Non-Diabetic | L3: =_xlfn.XLOOKUP($A3,'Cleaned - Hospitalisation Detai'!$A$2:$A$2344,'Cleaned - Hospitalisation Detai'!$J$2:$J$2344,0) -> 28284 | M3: =_xlfn.XLOOKUP($A3,'Cleaned - Hospitalisation Detai'!$A$2:$A$2344,'Cleaned - Hospitalisation Detai'!$F$2:$F$2344,0) -> 62592.87 | N3: =_xlfn.XLOOKUP($A3,'Cleaned - Hospitalisation Detai'!$A$2:$A$2344,'Cleaned - Hospitalisation Detai'!$G$2:$G$2344,0) -> tier - 2 | O3: =_xlfn.XLOOKUP($A3,'Cleaned - Hospitalisation Detai'!$A$2:$A$2344,'Cleaned - Hospitalisation Detai'!$H$2:$H$2344,0) -> tier - 3 | P3: =_xlfn.XLOOKUP($A3,'Cleaned - Hospitalisation Detai'!$A$2:$A$2344,'Cleaned - Hospitalisation Detai'!$I$2:$I$2344,0) -> R1013 | Q3: =_xlfn.XLOOKUP($A3,'Cleaned - Hospitalisation Detai'!$A$2:$A$2344,'Cleaned - Hospitalisation Detai'!$K$2:$K$2344,0) -> 46
A4: Id3 | B4: =_xlfn.XLOOKUP(A4,'Cleaned - Customer Names '!$A$2:$A$2336,'Cleaned - Customer Names '!$C$2:$C$2336,0) -> Phil | C4: =_xlfn.XLOOKUP($A4,'Cleaned - Medical Examinations'!$A$2:$A$2336,'Cleaned - Medical Examinations'!$B$2:$B$2336,0) -> 34.485 | D4: =_xlfn.XLOOKUP($A4,'Cleaned - Medical Examinations'!$A$2:$A$2336,'Cleaned - Medical Examinations'!$C$2:$C$2336,0) -> 11.87 | E4: =_xlfn.XLOOKUP($A4,'Cleaned - Medical Examinations'!$A$2:$A$2336,'Cleaned - Medical Examinations'!$D$2:$D$2336,0) -> Yes | F4: =_xlfn.XLOOKUP($A4,'Cleaned - Medical Examinations'!$A$2:$A$2336,'Cleaned - Medical Examinations'!$E$2:$E$2336,0) -> No | G4: =_xlfn.XLOOKUP($A4,'Cleaned - Medical Examinations'!$A$2:$A$2336,'Cleaned - Medical Examinations'!$F$2:$F$2336,0) -> No | H4: =_xlfn.XLOOKUP($A4,'Cleaned - Medical Examinations'!$A$2:$A$2336,'Cleaned - Medical Examinations'!$G$2:$G$2336,0) -> 2 | I4: =_xlfn.XLOOKUP($A4,'Cleaned - Medical Examinations'!$A$2:$A$2336,'Cleaned - Medical Examinations'!$H$2:$H$2336,0) -> Yes | J4: =_xlfn.XLOOKUP($A4,'Cleaned - Medical Examinations'!$A$2:$A$2336,'Cleaned - Medical Examinations'!$I$2:$I$2336,0) -> Obesity | K4: =IF(D4>=6.5,"Diabetic","Non-Diabetic") -> Diabetic | L4: =_xlfn.XLOOKUP($A4,'Cleaned - Hospitalisation Detai'!$A$2:$A$2344,'Cleaned - Hospitalisation Detai'!$J$2:$J$2344,0) -> 25822 | M4: =_xlfn.XLOOKUP($A4,'Cleaned - Hospitalisation Detai'!$A$2:$A$2344,'Cleaned - Hospitalisation Detai'!$F$2:$F$2344,0) -> 60021.4 | N4: =_xlfn.XLOOKUP($A4,'Cleaned - Hospitalisation Detai'!$A$2:$A$2344,'Cleaned - Hospitalisation Detai'!$G$2:$G$2344,0) -> tier - 1 | O4: =_xlfn.XLOOKUP($A4,'Cleaned - Hospitalisation Detai'!$A$2:$A$2344,'Cleaned - Hospitalisation Detai'!$H$2:$H$2344,0) -> tier - 1 | P4: =_xlfn.XLOOKUP($A4,'Cleaned - Hospitalisation Detai'!$A$2:$A$2344,'Cleaned - Hospitalisation Detai'!$I$2:$I$2344,0) -> R1012 | Q4: =_xlfn.XLOOKUP($A4,'Cleaned - Hospitalisation Detai'!$A$2:$A$2344,'Cleaned - Hospitalisation Detai'!$K$2:$K$2344,0) -> 52
A5: Id4 | B5: =_xlfn.XLOOKUP(A5,'Cleaned - Customer Names '!$A$2:$A$2336,'Cleaned - Customer Names '!$C$2:$C$2336,0) -> Kelsey | C5: =_xlfn.XLOOKUP($A5,'Cleaned - Medical Examinations'!$A$2:$A$2336,'Cleaned - Medical Examinations'!$B$2:$B$2336,0) -> 38.095 | D5: =_xlfn.XLOOKUP($A5,'Cleaned - Medical Examinations'!$A$2:$A$2336,'Cleaned - Medical Examinations'!$C$2:$C$2336,0) -> 6.05 | E5: =_xlfn.XLOOKUP($A5,'Cleaned - Medical Examinations'!$A$2:$A$2336,'Cleaned - Medical Examinations'!$D$2:$D$2336,0) -> No | F5: =_xlfn.XLOOKUP($A5,'Cleaned - Medical Examinations'!$A$2:$A$2336,'Cleaned - Medical Examinations'!$E$2:$E$2336,0) -> No | G5: =_xlfn.XLOOKUP($A5,'Cleaned - Medical Examinations'!$A$2:$A$2336,'Cleaned - Medical Examinations'!$F$2:$F$2336,0) -> No | H5: =_xlfn.XLOOKUP($A5,'Cleaned - Medical Examinations'!$A$2:$A$2336,'Cleaned - Medical Examinations'!$G$2:$G$2336,0) -> 0 | I5: =_xlfn.XLOOKUP($A5,'Cleaned - Medical Examinations'!$A$2:$A$2336,'Cleaned - Medical Examinations'!$H$2:$H$2336,0) -> Yes | J5: =_xlfn.XLOOKUP($A5,'Cleaned - Medical Examinations'!$A$2:$A$2336,'Cleaned - Medical Examinations'!$I$2:$I$2336,0) -> Obesity | K5: =IF(D5>=6.5,"Diabetic","Non-Diabetic") -> Non-Diabetic | L5: =_xlfn.XLOOKUP($A5,'Cleaned - Hospitalisation Detai'!$A$2:$A$2344,'Cleaned - Hospitalisation Detai'!$J$2:$J$2344,0) -> 33395 | M5: =_xlfn.XLOOKUP($A5,'Cleaned - Hospitalisation Detai'!$A$2:$A$2344,'Cleaned - Hospitalisation Detai'!$F$2:$F$2344,0) -> 58571.07 | N5: =_xlfn.XLOOKUP($A5,'Cleaned - Hospitalisation Detai'!$A$2:$A$2344,'Cleaned - Hospitalisation Detai'!$G$2:$G$2344,0) -> tier - 1 | O5: =_xlfn.XLOOKUP($A5,'Cleaned - Hospitalisation Detai'!$A$2:$A$2344,'Cleaned - Hospitalisation Detai'!$H$2:$H$2344,0) -> tier - 3 | P5: =_xlfn.XLOOKUP($A5,'Cleaned - Hospitalisation Detai'!$A$2:$A$2344,'Cleaned - Hospitalisation Detai'!$I$2:$I$2344,0) -> R1024 | Q5: =_xlfn.XLOOKUP($A5,'Cleaned - Hospitalisation Detai'!$A$2:$A$2344,'Cleaned - Hospitalisation Detai'!$K$2:$K$2344,0) -> 32
A6: Id5 | B6: =_xlfn.XLOOKUP(A6,'Cleaned - Customer Names '!$A$2:$A$2336,'Cleaned - Customer Names '!$C$2:$C$2336,0) -> Kristyn | C6: =_xlfn.XLOOKUP($A6,'Cleaned - Medical Examinations'!$A$2:$A$2336,'Cleaned - Medical Examinations'!$B$2:$B$2336,0) -> 35.53 | D6: =_xlfn.XLOOKUP($A6,'Cleaned - Medical Examinations'!$A$2:$A$2336,'Cleaned - Medical Examinations'!$C$2:$C$2336,0) -> 5.45 | E6: =_xlfn.XLOOKUP($A6,'Cleaned - Medical Examinations'!$A$2:$A$2336,'Cleaned - Medical Examinations'!$D$2:$D$2336,0) -> No | F6: =_xlfn.XLOOKUP($A6,'Cleaned - Medical Examinations'!$A$2:$A$2336,'Cleaned - Medical Examinations'!$E$2:$E$2336,0) -> No | G6: =_xlfn.XLOOKUP($A6,'Cleaned - Medical Examinations'!$A$2:$A$2336,'Cleaned - Medical Examinations'!$F$2:$F$2336,0) -> No | H6: =_xlfn.XLOOKUP($A6,'Cleaned - Medical Examinations'!$A$2:$A$2336,'Cleaned - Medical Examinations'!$G$2:$G$2336,0) -> 0 | I6: =_xlfn.XLOOKUP($A6,'Cleaned - Medical Examinations'!$A$2:$A$2336,'Cleaned - Medical Examinations'!$H$2:$H$2336,0) -> Yes | J6: =_xlfn.XLOOKUP($A6,'Cleaned - Medical Examinations'!$A$2:$A$2336,'Cleaned - Medical Examinations'!$I$2:$I$2336,0) -> Obesity | K6: =IF(D6>=6.5,"Diabetic","Non-Diabetic") -> Non-Diabetic | L6: =_xlfn.XLOOKUP($A6,'Cleaned - Hospitalisation Detai'!$A$2:$A$2344,'Cleaned - Hospitalisation Detai'!$J$2:$J$2344,0) -> 32678 | M6: =_xlfn.XLOOKUP($A6,'Cleaned - Hospitalisation Detai'!$A$2:$A$2344,'Cleaned - Hospitalisation Detai'!$F$2:$F$2344,0) -> 55135.4 | N6: =_xlfn.XLOOKUP($A6,'Cleaned - Hospitalisation Detai'!$A$2:$A$2344,'Cleaned - Hospitalisation Detai'!$G$2:$G$2344,0) -> tier - 1 | O6: =_xlfn.XLOOKUP($A6,'Cleaned - Hospitalisation Detai'!$A$2:$A$2344,'Cleaned - Hospitalisation Detai'!$H$2:$H$2344,0) -> tier - 2 | P6: =_xlfn.XLOOKUP($A6,'Cleaned - Hospitalisation Detai'!$A$2:$A$2344,'Cleaned - Hospitalisation Detai'!$I$2:$I$2344,0) -> R1012 | Q6: =_xlfn.XLOOKUP($A6,'Cleaned - Hospitalisation Detai'!$A$2:$A$2344,'Cleaned - Hospitalisation Detai'!$K$2:$K$2344,0) -> 33
A7: Id6 | B7: =_xlfn.XLOOKUP(A7,'Cleaned - Customer Names '!$A$2:$A$2336,'Cleaned - Customer Names '!$C$2:$C$2336,0) -> Russell B. | C7: =_xlfn.XLOOKUP($A7,'Cleaned - Medical Examinations'!$A$2:$A$2336,'Cleaned - Medical Examinations'!$B$2:$B$2336,0) -> 32.8 | D7: =_xlfn.XLOOKUP($A7,'Cleaned - Medical Examinations'!$A$2:$A$2336,'Cleaned - Medical Examinations'!$C$2:$C$2336,0) -> 6.59 | E7: =_xlfn.XLOOKUP($A7,'Cleaned - Medical Examinations'!$A$2:$A$2336,'Cleaned - Medical Examinations'!$D$2:$D$2336,0) -> No | F7: =_xlfn.XLOOKUP($A7,'Cleaned - Medical Examinations'!$A$2:$A$2336,'Cleaned - Medical Examinations'!$E$2:$E$2336,0) -> No | G7: =_xlfn.XLOOKUP($A7,'Cleaned - Medical Examinations'!$A$2:$A$2336,'Cleaned - Medical Examinations'!$F$2:$F$2336,0) -> No | H7: =_xlfn.XLOOKUP($A7,'Cleaned - Medical Examinations'!$A$2:$A$2336,'Cleaned - Medical Examinations'!$G$2:$G$2336,0) -> 0 | I7: =_xlfn.XLOOKUP($A7,'Cleaned - Medical Examinations'!$A$2:$A$2336,'Cleaned - Medical Examinations'!$H$2:$H$2336,0) -> Yes | J7: =_xlfn.XLOOKUP($A7,'Cleaned - Medical Examinations'!$A$2:$A$2336,'Cleaned - Medical Examinations'!$I$2:$I$2336,0) -> Obesity | K7: =IF(D7>=6.5,"Diabetic","Non-Diabetic") -> Diabetic | L7: =_xlfn.XLOOKUP($A7,'Cleaned - Hospitalisation Detai'!$A$2:$A$2344,'Cleaned - Hospitalisation Detai'!$J$2:$J$2344,0) -> 22862 | M7: =_xlfn.XLOOKUP($A7,'Cleaned - Hospitalisation Detai'!$A$2:$A$2344,'Cleaned - Hospitalisation Detai'!$F$2:$F$2344,0) -> 52590.83 | N7: =_xlfn.XLOOKUP($A7,'Cleaned - Hospitalisation Detai'!$A$2:$A$2344,'Cleaned - Hospitalisation Detai'!$G$2:$G$2344,0) -> tier - 1 | O7: =_xlfn.XLOOKUP($A7,'Cleaned - Hospitalisation Detai'!$A$2:$A$2344,'Cleaned - Hospitalisation Detai'!$H$2:$H$2344,0) -> tier - 3 | P7: =_xlfn.XLOOKUP($A7,'Cleaned - Hospitalisation Detai'!$A$2:$A$2344,'Cleaned - Hospitalisation Detai'!$I$2:$I$2344,0) -> R1011 | Q7: =_xlfn.XLOOKUP($A7,'Cleaned - Hospitalisation Detai'!$A$2:$A$2344,'Cleaned - Hospitalisation Detai'!$K$2:$K$2344,0) -> 60
A8: Id7 | B8: =_xlfn.XLOOKUP(A8,'Cleaned - Customer Names '!$A$2:$A$2336,'Cleaned - Customer Names '!$C$2:$C$2336,0) -> Scott | C8: =_xlfn.XLOOKUP($A8,'Cleaned - Medical Examinations'!$A$2:$A$2336,'Cleaned - Medical Examinations'!$B$2:$B$2336,0) -> 36.4 | D8: =_xlfn.XLOOKUP($A8,'Cleaned - Medical Examinations'!$A$2:$A$2336,'Cleaned - Medical Examinations'!$C$2:$C$2336,0) -> 6.07 | E8: =_xlfn.XLOOKUP($A8,'Cleaned - Medical Examinations'!$A$2:$A$2336,'Cleaned - Medical Examinations'!$D$2:$D$2336,0) -> No | F8: =_xlfn.XLOOKUP($A8,'Cleaned - Medical Examinations'!$A$2:$A$2336,'Cleaned - Medical Examinations'!$E$2:$E$2336,0) -> No | G8: =_xlfn.XLOOKUP($A8,'Cleaned - Medical Examinations'!$A$2:$A$2336,'Cleaned - Medical Examinations'!$F$2:$F$2336,0) -> No | H8: =_xlfn.XLOOKUP($A8,'Cleaned - Medical Examinations'!$A$2:$A$2336,'Cleaned - Medical Examinations'!$G$2:$G$2336,0) -> 0 | I8: =_xlfn.XLOOKUP($A8,'Cleaned - Medical Examinations'!$A$2:$A$2336,'Cleaned - Medical Examinations'!$H$2:$H$2336,0) -> Yes | J8: =_xlfn.XLOOKUP($A8,'Cleaned - Medical Examinations'!$A$2:$A$2336,'Cleaned - Medical Examinations'!$I$2:$I$2336,0) -> Obesity | K8: =IF(D8>=6.5,"Diabetic","Non-Diabetic") -> Non-Diabetic | L8: =_xlfn.XLOOKUP($A8,'Cleaned - Hospitalisation Detai'!$A$2:$A$2344,'Cleaned - Hospitalisation Detai'!$J$2:$J$2344,0) -> 34634 | M8: =_xlfn.XLOOKUP($A8,'Cleaned - Hospitalisation Detai'!$A$2:$A$2344,'Cleaned - Hospitalisation Detai'!$F$2:$F$2344,0) -> 51194.56 | N8: =_xlfn.XLOOKUP($A8,'Cleaned - Hospitalisation Detai'!$A$2:$A$2344,'Cleaned - Hospitalisation Detai'!$G$2:$G$2344,0) -> tier - 1 | O8: =_xlfn.XLOOKUP($A8,'Cleaned - Hospitalisation Detai'!$A$2:$A$2344,'Cleaned - Hospitalisation Detai'!$H$2:$H$2344,0) -> tier - 3 | P8: =_xlfn.XLOOKUP($A8,'Cleaned - Hospitalisation Detai'!$A$2:$A$2344,'Cleaned - Hospitalisation Detai'!$I$2:$I$2344,0) -> R1011 | Q8: =_xlfn.XLOOKUP($A8,'Cleaned - Hospitalisation Detai'!$A$2:$A$2344,'Cleaned - Hospitalisation Detai'!$K$2:$K$2344,0) -> 28
A9: Id8 | B9: =_xlfn.XLOOKUP(A9,'Cleaned - Customer Names '!$A$2:$A$2336,'Cleaned - Customer Names '!$C$2:$C$2336,0) -> Stephen | C9: =_xlfn.XLOOKUP($A9,'Cleaned - Medical Examinations'!$A$2:$A$2336,'Cleaned - Medical Examinations'!$B$2:$B$2336,0) -> 36.96 | D9: =_xlfn.XLOOKUP($A9,'Cleaned - Medical Examinations'!$A$2:$A$2336,'Cleaned - Medical Examinations'!$C$2:$C$2336,0) -> 7.93 | E9: =_xlfn.XLOOKUP($A9,'Cleaned - Medical Examinations'!$A$2:$A$2336,'Cleaned - Medical Examinations'!$D$2:$D$2336,0) -> No | F9: =_xlfn.XLOOKUP($A9,'Cleaned - Medical Examinations'!$A$2:$A$2336,'Cleaned - Medical Examinations'!$E$2:$E$2336,0) -> No | G9: =_xlfn.XLOOKUP($A9,'Cleaned - Medical Examinations'!$A$2:$A$2336,'Cleaned - Medical Examinations'!$F$2:$F$2336,0) -> No | H9: =_xlfn.XLOOKUP($A9,'Cleaned - Medical Examinations'!$A$2:$A$2336,'Cleaned - Medical Examinations'!$G$2:$G$2336,0) -> 3 | I9: =_xlfn.XLOOKUP($A9,'Cleaned - Medical Examinations'!$A$2:$A$2336,'Cleaned - Medical Examinations'!$H$2:$H$2336,0) -> Yes | J9: =_xlfn.XLOOKUP($A9,'Cleaned - Medical Examinations'!$A$2:$A$2336,'Cleaned - Medical Examinations'!$I$2:$I$2336,0) -> Obesity | K9: =IF(D9>=6.5,"Diabetic","Non-Diabetic") -> Diabetic | L9: =_xlfn.XLOOKUP($A9,'Cleaned - Hospitalisation Detai'!$A$2:$A$2344,'Cleaned - Hospitalisation Detai'!$J$2:$J$2344,0) -> 21363 | M9: =_xlfn.XLOOKUP($A9,'Cleaned - Hospitalisation Detai'!$A$2:$A$2344,'Cleaned - Hospitalisation Detai'!$F$2:$F$2344,0) -> 49577.66 | N9: =_xlfn.XLOOKUP($A9,'Cleaned - Hospitalisation Detai'!$A$2:$A$2344,'Cleaned - Hospitalisation Detai'!$G$2:$G$2344,0) -> tier - 2 | O9: =_xlfn.XLOOKUP($A9,'Cleaned - Hospitalisation Detai'!$A$2:$A$2344,'Cleaned - Hospitalisation Detai'!$H$2:$H$2344,0) -> tier - 2 | P9: =_xlfn.XLOOKUP($A9,'Cleaned - Hospitalisation Detai'!$A$2:$A$2344,'Cleaned - Hospitalisation Detai'!$I$2:$I$2344,0) -> R1013 | Q9: =_xlfn.XLOOKUP($A9,'Cleaned - Hospitalisation Detai'!$A$2:$A$2344,'Cleaned - Hospitalisation Detai'!$K$2:$K$2344,0) -> 64
A10: Id9 | B10: =_xlfn.XLOOKUP(A10,'Cleaned - Customer Names '!$A$2:$A$2336,'Cleaned - Customer Names '!$C$2:$C$2336,0) -> Patrick R. | C10: =_xlfn.XLOOKUP($A10,'Cleaned - Medical Examinations'!$A$2:$A$2336,'Cleaned - Medical Examinations'!$B$2:$B$2336,0) -> 41.14 | D10: =_xlfn.XLOOKUP($A10,'Cleaned - Medical Examinations'!$A$2:$A$2336,'Cleaned - Medical Examinations'!$C$2:$C$2336,0) -> 9.58 | E10: =_xlfn.XLOOKUP($A10,'Cleaned - Medical Examinations'!$A$2:$A$2336,'Cleaned - Medical Examinations'!$D$2:$D$2336,0) -> Yes | F10: =_xlfn.XLOOKUP($A10,'Cleaned - Medical Examinations'!$A$2:$A$2336,'Cleaned - Medical Examinations'!$E$2:$E$2336,0) -> No | G10: =_xlfn.XLOOKUP($A10,'Cleaned - Medical Examinations'!$A$2:$A$2336,'Cleaned - Medical Examinations'!$F$2:$F$2336,0) -> Yes | H10: =_xlfn.XLOOKUP($A10,'Cleaned - Medical Examinations'!$A$2:$A$2336,'Cleaned - Medical Examinations'!$G$2:$G$2336,0) -> 1 | I10: =_xlfn.XLOOKUP($A10,'Cleaned - Medical Examinations'!$A$2:$A$2336,'Cleaned - Medical Examinations'!$H$2:$H$2336,0) -> Yes | J10: =_xlfn.XLOOKUP($A10,'Cleaned - Medical Examinations'!$A$2:$A$2336,'Cleaned - Medical Examinations'!$I$2:$I$2336,0) -> Obesity | K10: =IF(D10>=6.5,"Diabetic","Non-Diabetic") -> Diabetic | L10: =_xlfn.XLOOKUP($A10,'Cleaned - Hospitalisation Detai'!$A$2:$A$2344,'Cleaned - Hospitalisation Detai'!$J$2:$J$2344,0) -> 23258 | M10: =_xlfn.XLOOKUP($A10,'Cleaned - Hospitalisation Detai'!$A$2:$A$2344,'Cleaned - Hospitalisation Detai'!$F$2:$F$2344,0) -> 48970.25 | N10: =_xlfn.XLOOKUP($A10,'Cleaned - Hospitalisation Detai'!$A$2:$A$2344,'Cleaned - Hospitalisation Detai'!$G$2:$G$2344,0) -> tier - 1 | O10: =_xlfn.XLOOKUP($A10,'Cleaned - Hospitalisation Detai'!$A$2:$A$2344,'Cleaned - Hospitalisation Detai'!$H$2:$H$2344,0) -> tier - 2 | P10: =_xlfn.XLOOKUP($A10,'Cleaned - Hospitalisation Detai'!$A$2:$A$2344,'Cleaned - Hospitalisation Detai'!$I$2:$I$2344,0) -> R1013 | Q10: =_xlfn.XLOOKUP($A10,'Cleaned - Hospitalisation Detai'!$A$2:$A$2344,'Cleaned - Hospitalisation Detai'!$K$2:$K$2344,0) -> 59
A11: Id10 | B11: =_xlfn.XLOOKUP(A11,'Cleaned - Customer Names '!$A$2:$A$2336,'Cleaned - Customer Names '!$C$2:$C$2336,0) -> Brooke N. | C11: =_xlfn.XLOOKUP($A11,'Cleaned - Medical Examinations'!$A$2:$A$2336,'Cleaned - Medical Examinations'!$B$2:$B$2336,0) -> 38.06 | D11: =_xlfn.XLOOKUP($A11,'Cleaned - Medical Examinations'!$A$2:$A$2336,'Cleaned - Medical Examinations'!$C$2:$C$2336,0) -> 10.79 | E11: =_xlfn.XLOOKUP($A11,'Cleaned - Medical Examinations'!$A$2:$A$2336,'Cleaned - Medical Examinations'!$D$2:$D$2336,0) -> No | F11: =_xlfn.XLOOKUP($A11,'Cleaned - Medical Examinations'!$A$2:$A$2336,'Cleaned - Medical Examinations'!$E$2:$E$2336,0) -> No | G11: =_xlfn.XLOOKUP($A11,'Cleaned - Medical Examinations'!$A$2:$A$2336,'Cleaned - Medical Examinations'!$F$2:$F$2336,0) -> No | H11: =_xlfn.XLOOKUP($A11,'Cleaned - Medical Examinations'!$A$2:$A$2336,'Cleaned - Medical Examinations'!$G$2:$G$2336,0) -> 0 | I11: =_xlfn.XLOOKUP($A11,'Cleaned - Medical Examinations'!$A$2:$A$2336,'Cleaned - Medical Examinations'!$H$2:$H$2336,0) -> Yes | J11: =_xlfn.XLOOKUP($A11,'Cleaned - Medical Examinations'!$A$2:$A$2336,'Cleaned - Medical Examinations'!$I$2:$I$2336,0) -> Obesity | K11: =IF(D11>=6.5,"Diabetic","Non-Diabetic") -> Diabetic | L11: =_xlfn.XLOOKUP($A11,'Cleaned - Hospitalisation Detai'!$A$2:$A$2344,'Cleaned - Hospitalisation Detai'!$J$2:$J$2344,0) -> 28853 | M11: =_xlfn.XLOOKUP($A11,'Cleaned - Hospitalisation Detai'!$A$2:$A$2344,'Cleaned - Hospitalisation Detai'!$F$2:$F$2344,0) -> 48885.14 | N11: =_xlfn.XLOOKUP($A11,'Cleaned - Hospitalisation Detai'!$A$2:$A$2344,'Cleaned - Hospitalisation Detai'!$G$2:$G$2344,0) -> tier - 1 | O11: =_xlfn.XLOOKUP($A11,'Cleaned - Hospitalisation Detai'!$A$2:$A$2344,'Cleaned - Hospitalisation Detai'!$H$2:$H$2344,0) -> tier - 2 | P11: =_xlfn.XLOOKUP($A11,'Cleaned - Hospitalisation Detai'!$A$2:$A$2344,'Cleaned - Hospitalisation Detai'!$I$2:$I$2344,0) -> R1013 | Q11: =_xlfn.XLOOKUP($A11,'Cleaned - Hospitalisation Detai'!$A$2:$A$2344,'Cleaned - Hospitalisation Detai'!$K$2:$K$2344,0) -> 44
A12: Id11 | B12: =_xlfn.XLOOKUP(A12,'Cleaned - Customer Names '!$A$2:$A$2336,'Cleaned - Customer Names '!$C$2:$C$2336,0) -> Paola Andrea | C12: =_xlfn.XLOOKUP($A12,'Cleaned - Medical Examinations'!$A$2:$A$2336,'Cleaned - Medical Examinations'!$B$2:$B$2336,0) -> 37.7 | D12: =_xlfn.XLOOKUP($A12,'Cleaned - Medical Examinations'!$A$2:$A$2336,'Cleaned - Medical Examinations'!$C$2:$C$2336,0) -> 5.96 | E12: =_xlfn.XLOOKUP($A12,'Cleaned - Medical Examinations'!$A$2:$A$2336,'Cleaned - Medical Examinations'!$D$2:$D$2336,0) -> Yes | F12: =_xlfn.XLOOKUP($A12,'Cleaned - Medical Examinations'!$A$2:$A$2336,'Cleaned - Medical Examinations'!$E$2:$E$2336,0) -> No | G12: =_xlfn.XLOOKUP($A12,'Cleaned - Medical Examinations'!$A$2:$A$2336,'Cleaned - Medical Examinations'!$F$2:$F$2336,0) -> No | H12: =_xlfn.XLOOKUP($A12,'Cleaned - Medical Examinations'!$A$2:$A$2336,'Cleaned - Medical Examinations'!$G$2:$G$2336,0) -> 2 | I12: =_xlfn.XLOOKUP($A12,'Cleaned - Medical Examinations'!$A$2:$A$2336,'Cleaned - Medical Examinations'!$H$2:$H$2336,0) -> Yes | J12: =_xlfn.XLOOKUP($A12,'Cleaned - Medical Examinations'!$A$2:$A$2336,'Cleaned - Medical Examinations'!$I$2:$I$2336,0) -> Obesity | K12: =IF(D12>=6.5,"Diabetic","Non-Diabetic") -> Non-Diabetic | L12: =_xlfn.XLOOKUP($A12,'Cleaned - Hospitalisation Detai'!$A$2:$A$2344,'Cleaned - Hospitalisation Detai'!$J$2:$J$2344,0) -> 21753 | M12: =_xlfn.XLOOKUP($A12,'Cleaned - Hospitalisation Detai'!$A$2:$A$2344,'Cleaned - Hospitalisation Detai'!$F$2:$F$2344,0) -> 48824.45 | N12: =_xlfn.XLOOKUP($A12,'Cleaned - Hospitalisation Detai'!$A$2:$A$2344,'Cleaned - Hospitalisation Detai'!$G$2:$G$2344,0) -> tier - 2 | O12: =_xlfn.XLOOKUP($A12,'Cleaned - Hospitalisation Detai'!$A$2:$A$2344,'Cleaned - Hospitalisation Detai'!$H$2:$H$2344,0) -> tier - 1 | P12: =_xlfn.XLOOKUP($A12,'Cleaned - Hospitalisation Detai'!$A$2:$A$2344,'Cleaned - Hospitalisation Detai'!$I$2:$I$2344,0) -> R1011 | Q12: =_xlfn.XLOOKUP($A12,'Cleaned - Hospitalisation Detai'!$A$2:$A$2344,'Cleaned - Hospitalisation Detai'!$K$2:$K$2344,0) -> 63
A13: Id12 | B13: =_xlfn.XLOOKUP(A13,'Cleaned - Customer Names '!$A$2:$A$2336,'Cleaned - Customer Names '!$C$2:$C$2336,0) -> David | C13: =_xlfn.XLOOKUP($A13,'Cleaned - Medical Examinations'!$A$2:$A$2336,'Cleaned - Medical Examinations'!$B$2:$B$2336,0) -> 42.13 | D13: =_xlfn.XLOOKUP($A13,'Cleaned - Medical Examinations'!$A$2:$A$2336,'Cleaned - Medical Examinations'!$C$2:$C$2336,0) -> 11.9 | E13: =_xlfn.XLOOKUP($A13,'Cleaned - Medical Examinations'!$A$2:$A$2336,'Cleaned - Medical Examinations'!$D$2:$D$2336,0) -> No | F13: =_xlfn.XLOOKUP($A13,'Cleaned - Medical Examinations'!$A$2:$A$2336,'Cleaned - Medical Examinations'!$E$2:$E$2336,0) -> No | G13: =_xlfn.XLOOKUP($A13,'Cleaned - Medical Examinations'!$A$2:$A$2336,'Cleaned - Medical Examinations'!$F$2:$F$2336,0) -> No | H13: =_xlfn.XLOOKUP($A13,'Cleaned - Medical Examinations'!$A$2:$A$2336,'Cleaned - Medical Examinations'!$G$2:$G$2336,0) -> 0 | I13: =_xlfn.XLOOKUP($A13,'Cleaned - Medical Examinations'!$A$2:$A$2336,'Cleaned - Medical Examinations'!$H$2:$H$2336,0) -> Yes | J13: =_xlfn.XLOOKUP($A13,'Cleaned - Medical Examinations'!$A$2:$A$2336,'Cleaned - Medical Examinations'!$I$2:$I$2336,0) -> Obesity | K13: =IF(D13>=6.5,"Diabetic","Non-Diabetic") -> Diabetic | L13: =_xlfn.XLOOKUP($A13,'Cleaned - Hospitalisation Detai'!$A$2:$A$2344,'Cleaned - Hospitalisation Detai'!$J$2:$J$2344,0) -> 24042 | M13: =_xlfn.XLOOKUP($A13,'Cleaned - Hospitalisation Detai'!$A$2:$A$2344,'Cleaned - Hospitalisation Detai'!$F$2:$F$2344,0) -> 48675.52 | N13: =_xlfn.XLOOKUP($A13,'Cleaned - Hospitalisation Detai'!$A$2:$A$2344,'Cleaned - Hospitalisation Detai'!$G$2:$G$2344,0) -> tier - 1 | O13: =_xlfn.XLOOKUP($A13,'Cleaned - Hospitalisation Detai'!$A$2:$A$2344,'Cleaned - Hospitalisation Detai'!$H$2:$H$2344,0) -> tier - 2 | P13: =_xlfn.XLOOKUP($A13,'Cleaned - Hospitalisation Detai'!$A$2:$A$2344,'Cleaned - Hospitalisation Detai'!$I$2:$I$2344,0) -> R1013 | Q13: =_xlfn.XLOOKUP($A13,'Cleaned - Hospitalisation Detai'!$A$2:$A$2344,'Cleaned - Hospitalisation Detai'!$K$2:$K$2344,0) -> 57
... A2336: Id2335 | B2336: =_xlfn.XLOOKUP(A2336,'Cleaned - Customer Names '!$A$2:$A$2336,'Cleaned - Customer Names '!$C$2:$C$2336,0) -> Aaron K | C2336: =_xlfn.XLOOKUP($A2336,'Cleaned - Medical Examinations'!$A$2:$A$2336,'Cleaned - Medical Examinations'!$B$2:$B$2336,0) -> 17.58 | D2336: =_xlfn.XLOOKUP($A2336,'Cleaned - Medical Examinations'!$A$2:$A$2336,'Cleaned - Medical Examinations'!$C$2:$C$2336,0) -> 4.51 | E2336: =_xlfn.XLOOKUP($A2336,'Cleaned - Medical Examinations'!$A$2:$A$2336,'Cleaned - Medical Examinations'!$D$2:$D$2336,0) -> No | F2336: =_xlfn.XLOOKUP($A2336,'Cleaned - Medical Examinations'!$A$2:$A$2336,'Cleaned - Medical Examinations'!$E$2:$E$2336,0) -> No | G2336: =_xlfn.XLOOKUP($A2336,'Cleaned - Medical Examinations'!$A$2:$A$2336,'Cleaned - Medical Examinations'!$F$2:$F$2336,0) -> No | H2336: =_xlfn.XLOOKUP($A2336,'Cleaned - Medical Examinations'!$A$2:$A$2336,'Cleaned - Medical Examinations'!$G$2:$G$2336,0) -> 1 | I2336: =_xlfn.XLOOKUP($A2336,'Cleaned - Medical Examinations'!$A$2:$A$2336,'Cleaned - Medical Examinations'!$H$2:$H$2336,0) -> No | J2336: =_xlfn.XLOOKUP($A2336,'Cleaned - Medical Examinations'!$A$2:$A$2336,'Cleaned - Medical Examinations'!$I$2:$I$2336,0) -> Underweight | K2336: =IF(D2336>=6.5,"Diabetic","Non-Diabetic") -> Non-Diabetic | L2336: =_xlfn.XLOOKUP($A2336,'Cleaned - Hospitalisation Detai'!$A$2:$A$2344,'Cleaned - Hospitalisation Detai'!$J$2:$J$2344,0) -> 33794 | M2336: =_xlfn.XLOOKUP($A2336,'Cleaned - Hospitalisation Detai'!$A$2:$A$2344,'Cleaned - Hospitalisation Detai'!$F$2:$F$2344,0) -> 563.84 | N2336: =_xlfn.XLOOKUP($A2336,'Cleaned - Hospitalisation Detai'!$A$2:$A$2344,'Cleaned - Hospitalisation Detai'!$G$2:$G$2344,0) -> tier - 2 | O2336: =_xlfn.XLOOKUP($A2336,'Cleaned - Hospitalisation Detai'!$A$2:$A$2344,'Cleaned - Hospitalisation Detai'!$H$2:$H$2344,0) -> tier - 3 | P2336: =_xlfn.XLOOKUP($A2336,'Cleaned - Hospitalisation Detai'!$A$2:$A$2344,'Cleaned - Hospitalisation Detai'!$I$2:$I$2344,0) -> R1013 | Q2336: =_xlfn.XLOOKUP($A2336,'Cleaned - Hospitalisation Detai'!$A$2:$A$2344,'Cleaned - Hospitalisation Detai'!$K$2:$K$2344,0) -> 30

Sheet New - Health Care
A1: Customer ID | B1: First Name | C1: BMI | D1: HBA1C | E1: Heart Issues | F1: Any Transplants | G1: Cancer History | H1: Number of Major Surgeries | I1: Smoker | J1: Weight Status | K1: Diabetes Status | L1: Date of Birth | M1: Charges | N1: Hospital Tier | O1: City Tier | P1: State ID | Q1: Age
A2: Id1 | B2: =_xlfn.XLOOKUP(A2,'Cleaned - Customer Names '!$A$2:$A$2336,'Cleaned - Customer Names '!$C$2:$C$2336,0) -> Kelly | C2: =_xlfn.XLOOKUP($A2,'Cleaned - Medical Examinations'!$A$2:$A$2336,'Cleaned - Medical Examinations'!$B$2:$B$2336,0) -> 47.41 | D2: =_xlfn.XLOOKUP($A2,'Cleaned - Medical Examinations'!$A$2:$A$2336,'Cleaned - Medical Examinations'!$C$2:$C$2336,0) -> 7.47 | E2: =_xlfn.XLOOKUP($A2,'Cleaned - Medical Examinations'!$A$2:$A$2336,'Cleaned - Medical Examinations'!$D$2:$D$2336,0) -> No | F2: =_xlfn.XLOOKUP($A2,'Cleaned - Medical Examinations'!$A$2:$A$2336,'Cleaned - Medical Examinations'!$E$2:$E$2336,0) -> No | G2: =_xlfn.XLOOKUP($A2,'Cleaned - Medical Examinations'!$A$2:$A$2336,'Cleaned - Medical Examinations'!$F$2:$F$2336,0) -> No | H2: =_xlfn.XLOOKUP($A2,'Cleaned - Medical Examinations'!$A$2:$A$2336,'Cleaned - Medical Examinations'!$G$2:$G$2336,0) -> 0 | I2: =_xlfn.XLOOKUP($A2,'Cleaned - Medical Examinations'!$A$2:$A$2336,'Cleaned - Medical Examinations'!$H$2:$H$2336,0) -> Yes | J2: =_xlfn.XLOOKUP($A2,'Cleaned - Medical Examinations'!$A$2:$A$2336,'Cleaned - Medical Examinations'!$I$2:$I$2336,0) -> Obesity | K2: =IF(D2>=6.5,"Diabetic","Non-Diabetic") -> Diabetic | L2: =_xlfn.XLOOKUP($A2,'Cleaned - Hospitalisation Detai'!$A$2:$A$2344,'Cleaned - Hospitalisation Detai'!$J$2:$J$2344,0) -> 25123 | M2: =_xlfn.XLOOKUP($A2,'Cleaned - Hospitalisation Detai'!$A$2:$A$2344,'Cleaned - Hospitalisation Detai'!$F$2:$F$2344,0) -> 63770.43 | N2: =_xlfn.XLOOKUP($A2,'Cleaned - Hospitalisation Detai'!$A$2:$A$2344,'Cleaned - Hospitalisation Detai'!$G$2:$G$2344,0) -> tier - 1 | O2: =_xlfn.XLOOKUP($A2,'Cleaned - Hospitalisation Detai'!$A$2:$A$2344,'Cleaned - Hospitalisation Detai'!$H$2:$H$2344,0) -> tier - 3 | P2: =_xlfn.XLOOKUP($A2,'Cleaned - Hospitalisation Detai'!$A$2:$A$2344,'Cleaned - Hospitalisation Detai'!$I$2:$I$2344,0) -> R1013 | Q2: =_xlfn.XLOOKUP($A2,'Cleaned - Hospitalisation Detai'!$A$2:$A$2344,'Cleaned - Hospitalisation Detai'!$K$2:$K$2344,0) -> 54
A3: Id2 | B3: =_xlfn.XLOOKUP(A3,'Cleaned - Customer Names '!$A$2:$A$2336,'Cleaned - Customer Names '!$C$2:$C$2336,0) -> Matthew D | C3: =_xlfn.XLOOKUP($A3,'Cleaned - Medical Examinations'!$A$2:$A$2336,'Cleaned - Medical Examinations'!$B$2:$B$2336,0) -> 30.36 | D3: =_xlfn.XLOOKUP($A3,'Cleaned - Medical Examinations'!$A$2:$A$2336,'Cleaned - Medical Examinations'!$C$2:$C$2336,0) -> 5.77 | E3: =_xlfn.XLOOKUP($A3,'Cleaned - Medical Examinations'!$A$2:$A$2336,'Cleaned - Medical Examinations'!$D$2:$D$2336,0) -> No | F3: =_xlfn.XLOOKUP($A3,'Cleaned - Medical Examinations'!$A$2:$A$2336,'Cleaned - Medical Examinations'!$E$2:$E$2336,0) -> No | G3: =_xlfn.XLOOKUP($A3,'Cleaned - Medical Examinations'!$A$2:$A$2336,'Cleaned - Medical Examinations'!$F$2:$F$2336,0) -> No | H3: =_xlfn.XLOOKUP($A3,'Cleaned - Medical Examinations'!$A$2:$A$2336,'Cleaned - Medical Examinations'!$G$2:$G$2336,0) -> 0 | I3: =_xlfn.XLOOKUP($A3,'Cleaned - Medical Examinations'!$A$2:$A$2336,'Cleaned - Medical Examinations'!$H$2:$H$2336,0) -> Yes | J3: =_xlfn.XLOOKUP($A3,'Cleaned - Medical Examinations'!$A$2:$A$2336,'Cleaned - Medical Examinations'!$I$2:$I$2336,0) -> Obesity | K3: =IF(D3>=6.5,"Diabetic","Non-Diabetic") -> Non-Diabetic | L3: =_xlfn.XLOOKUP($A3,'Cleaned - Hospitalisation Detai'!$A$2:$A$2344,'Cleaned - Hospitalisation Detai'!$J$2:$J$2344,0) -> 28284 | M3: =_xlfn.XLOOKUP($A3,'Cleaned - Hospitalisation Detai'!$A$2:$A$2344,'Cleaned - Hospitalisation Detai'!$F$2:$F$2344,0) -> 62592.87 | N3: =_xlfn.XLOOKUP($A3,'Cleaned - Hospitalisation Detai'!$A$2:$A$2344,'Cleaned - Hospitalisation Detai'!$G$2:$G$2344,0) -> tier - 2 | O3: =_xlfn.XLOOKUP($A3,'Cleaned - Hospitalisation Detai'!$A$2:$A$2344,'Cleaned - Hospitalisation Detai'!$H$2:$H$2344,0) -> tier - 3 | P3: =_xlfn.XLOOKUP($A3,'Cleaned - Hospitalisation Detai'!$A$2:$A$2344,'Cleaned - Hospitalisation Detai'!$I$2:$I$2344,0) -> R1013 | Q3: =_xlfn.XLOOKUP($A3,'Cleaned - Hospitalisation Detai'!$A$2:$A$2344,'Cleaned - Hospitalisation Detai'!$K$2:$K$2344,0) -> 46
A4: Id3 | B4: =_xlfn.XLOOKUP(A4,'Cleaned - Customer Names '!$A$2:$A$2336,'Cleaned - Customer Names '!$C$2:$C$2336,0) -> Phil | C4: =_xlfn.XLOOKUP($A4,'Cleaned - Medical Examinations'!$A$2:$A$2336,'Cleaned - Medical Examinations'!$B$2:$B$2336,0) -> 34.485 | D4: =_xlfn.XLOOKUP($A4,'Cleaned - Medical Examinations'!$A$2:$A$2336,'Cleaned - Medical Examinations'!$C$2:$C$2336,0) -> 11.87 | E4: =_xlfn.XLOOKUP($A4,'Cleaned - Medical Examinations'!$A$2:$A$2336,'Cleaned - Medical Examinations'!$D$2:$D$2336,0) -> Yes | F4: =_xlfn.XLOOKUP($A4,'Cleaned - Medical Examinations'!$A$2:$A$2336,'Cleaned - Medical Examinations'!$E$2:$E$2336,0) -> No | G4: =_xlfn.XLOOKUP($A4,'Cleaned - Medical Examinations'!$A$2:$A$2336,'Cleaned - Medical Examinations'!$F$2:$F$2336,0) -> No | H4: =_xlfn.XLOOKUP($A4,'Cleaned - Medical Examinations'!$A$2:$A$2336,'Cleaned - Medical Examinations'!$G$2:$G$2336,0) -> 2 | I4: =_xlfn.XLOOKUP($A4,'Cleaned - Medical Examinations'!$A$2:$A$2336,'Cleaned - Medical Examinations'!$H$2:$H$2336,0) -> Yes | J4: =_xlfn.XLOOKUP($A4,'Cleaned - Medical Examinations'!$A$2:$A$2336,'Cleaned - Medical Examinations'!$I$2:$I$2336,0) -> Obesity | K4: =IF(D4>=6.5,"Diabetic","Non-Diabetic") -> Diabetic | L4: =_xlfn.XLOOKUP($A4,'Cleaned - Hospitalisation Detai'!$A$2:$A$2344,'Cleaned - Hospitalisation Detai'!$J$2:$J$2344,0) -> 25822 | M4: =_xlfn.XLOOKUP($A4,'Cleaned - Hospitalisation Detai'!$A$2:$A$2344,'Cleaned - Hospitalisation Detai'!$F$2:$F$2344,0) -> 60021.4 | N4: =_xlfn.XLOOKUP($A4,'Cleaned - Hospitalisation Detai'!$A$2:$A$2344,'Cleaned - Hospitalisation Detai'!$G$2:$G$2344,0) -> tier - 1 | O4: =_xlfn.XLOOKUP($A4,'Cleaned - Hospitalisation Detai'!$A$2:$A$2344,'Cleaned - Hospitalisation Detai'!$H$2:$H$2344,0) -> tier - 1 | P4: =_xlfn.XLOOKUP($A4,'Cleaned - Hospitalisation Detai'!$A$2:$A$2344,'Cleaned - Hospitalisation Detai'!$I$2:$I$2344,0) -> R1012 | Q4: =_xlfn.XLOOKUP($A4,'Cleaned - Hospitalisation Detai'!$A$2:$A$2344,'Cleaned - Hospitalisation Detai'!$K$2:$K$2344,0) -> 52
A5: Id4 | B5: =_xlfn.XLOOKUP(A5,'Cleaned - Customer Names '!$A$2:$A$2336,'Cleaned - Customer Names '!$C$2:$C$2336,0) -> Kelsey | C5: =_xlfn.XLOOKUP($A5,'Cleaned - Medical Examinations'!$A$2:$A$2336,'Cleaned - Medical Examinations'!$B$2:$B$2336,0) -> 38.095 | D5: =_xlfn.XLOOKUP($A5,'Cleaned - Medical Examinations'!$A$2:$A$2336,'Cleaned - Medical Examinations'!$C$2:$C$2336,0) -> 6.05 | E5: =_xlfn.XLOOKUP($A5,'Cleaned - Medical Examinations'!$A$2:$A$2336,'Cleaned - Medical Examinations'!$D$2:$D$2336,0) -> No | F5: =_xlfn.XLOOKUP($A5,'Cleaned - Medical Examinations'!$A$2:$A$2336,'Cleaned - Medical Examinations'!$E$2:$E$2336,0) -> No | G5: =_xlfn.XLOOKUP($A5,'Cleaned - Medical Examinations'!$A$2:$A$2336,'Cleaned - Medical Examinations'!$F$2:$F$2336,0) -> No | H5: =_xlfn.XLOOKUP($A5,'Cleaned - Medical Examinations'!$A$2:$A$2336,'Cleaned - Medical Examinations'!$G$2:$G$2336,0) -> 0 | I5: =_xlfn.XLOOKUP($A5,'Cleaned - Medical Examinations'!$A$2:$A$2336,'Cleaned - Medical Examinations'!$H$2:$H$2336,0) -> Yes | J5: =_xlfn.XLOOKUP($A5,'Cleaned - Medical Examinations'!$A$2:$A$2336,'Cleaned - Medical Examinations'!$I$2:$I$2336,0) -> Obesity | K5: =IF(D5>=6.5,"Diabetic","Non-Diabetic") -> Non-Diabetic | L5: =_xlfn.XLOOKUP($A5,'Cleaned - Hospitalisation Detai'!$A$2:$A$2344,'Cleaned - Hospitalisation Detai'!$J$2:$J$2344,0) -> 33395 | M5: =_xlfn.XLOOKUP($A5,'Cleaned - Hospitalisation Detai'!$A$2:$A$2344,'Cleaned - Hospitalisation Detai'!$F$2:$F$2344,0) -> 58571.07 | N5: =_xlfn.XLOOKUP($A5,'Cleaned - Hospitalisation Detai'!$A$2:$A$2344,'Cleaned - Hospitalisation Detai'!$G$2:$G$2344,0) -> tier - 1 | O5: =_xlfn.XLOOKUP($A5,'Cleaned - Hospitalisation Detai'!$A$2:$A$2344,'Cleaned - Hospitalisation Detai'!$H$2:$H$2344,0) -> tier - 3 | P5: =_xlfn.XLOOKUP($A5,'Cleaned - Hospitalisation Detai'!$A$2:$A$2344,'Cleaned - Hospitalisation Detai'!$I$2:$I$2344,0) -> R1024 | Q5: =_xlfn.XLOOKUP($A5,'Cleaned - Hospitalisation Detai'!$A$2:$A$2344,'Cleaned - Hospitalisation Detai'!$K$2:$K$2344,0) -> 32
A6: Id5 | B6: =_xlfn.XLOOKUP(A6,'Cleaned - Customer Names '!$A$2:$A$2336,'Cleaned - Customer Names '!$C$2:$C$2336,0) -> Kristyn | C6: =_xlfn.XLOOKUP($A6,'Cleaned - Medical Examinations'!$A$2:$A$2336,'Cleaned - Medical Examinations'!$B$2:$B$2336,0) -> 35.53 | D6: =_xlfn.XLOOKUP($A6,'Cleaned - Medical Examinations'!$A$2:$A$2336,'Cleaned - Medical Examinations'!$C$2:$C$2336,0) -> 5.45 | E6: =_xlfn.XLOOKUP($A6,'Cleaned - Medical Examinations'!$A$2:$A$2336,'Cleaned - Medical Examinations'!$D$2:$D$2336,0) -> No | F6: =_xlfn.XLOOKUP($A6,'Cleaned - Medical Examinations'!$A$2:$A$2336,'Cleaned - Medical Examinations'!$E$2:$E$2336,0) -> No | G6: =_xlfn.XLOOKUP($A6,'Cleaned - Medical Examinations'!$A$2:$A$2336,'Cleaned - Medical Examinations'!$F$2:$F$2336,0) -> No | H6: =_xlfn.XLOOKUP($A6,'Cleaned - Medical Examinations'!$A$2:$A$2336,'Cleaned - Medical Examinations'!$G$2:$G$2336,0) -> 0 | I6: =_xlfn.XLOOKUP($A6,'Cleaned - Medical Examinations'!$A$2:$A$2336,'Cleaned - Medical Examinations'!$H$2:$H$2336,0) -> Yes | J6: =_xlfn.XLOOKUP($A6,'Cleaned - Medical Examinations'!$A$2:$A$2336,'Cleaned - Medical Examinations'!$I$2:$I$2336,0) -> Obesity | K6: =IF(D6>=6.5,"Diabetic","Non-Diabetic") -> Non-Diabetic | L6: =_xlfn.XLOOKUP($A6,'Cleaned - Hospitalisation Detai'!$A$2:$A$2344,'Cleaned - Hospitalisation Detai'!$J$2:$J$2344,0) -> 32678 | M6: =_xlfn.XLOOKUP($A6,'Cleaned - Hospitalisation Detai'!$A$2:$A$2344,'Cleaned - Hospitalisation Detai'!$F$2:$F$2344,0) -> 55135.4 | N6: =_xlfn.XLOOKUP($A6,'Cleaned - Hospitalisation Detai'!$A$2:$A$2344,'Cleaned - Hospitalisation Detai'!$G$2:$G$2344,0) -> tier - 1 | O6: =_xlfn.XLOOKUP($A6,'Cleaned - Hospitalisation Detai'!$A$2:$A$2344,'Cleaned - Hospitalisation Detai'!$H$2:$H$2344,0) -> tier - 2 | P6: =_xlfn.XLOOKUP($A6,'Cleaned - Hospitalisation Detai'!$A$2:$A$2344,'Cleaned - Hospitalisation Detai'!$I$2:$I$2344,0) -> R1012 | Q6: =_xlfn.XLOOKUP($A6,'Cleaned - Hospitalisation Detai'!$A$2:$A$2344,'Cleaned - Hospitalisation Detai'!$K$2:$K$2344,0) -> 33
A7: Id6 | B7: =_xlfn.XLOOKUP(A7,'Cleaned - Customer Names '!$A$2:$A$2336,'Cleaned - Customer Names '!$C$2:$C$2336,0) -> Russell B. | C7: =_xlfn.XLOOKUP($A7,'Cleaned - Medical Examinations'!$A$2:$A$2336,'Cleaned - Medical Examinations'!$B$2:$B$2336,0) -> 32.8 | D7: =_xlfn.XLOOKUP($A7,'Cleaned - Medical Examinations'!$A$2:$A$2336,'Cleaned - Medical Examinations'!$C$2:$C$2336,0) -> 6.59 | E7: =_xlfn.XLOOKUP($A7,'Cleaned - Medical Examinations'!$A$2:$A$2336,'Cleaned - Medical Examinations'!$D$2:$D$2336,0) -> No | F7: =_xlfn.XLOOKUP($A7,'Cleaned - Medical Examinations'!$A$2:$A$2336,'Cleaned - Medical Examinations'!$E$2:$E$2336,0) -> No | G7: =_xlfn.XLOOKUP($A7,'Cleaned - Medical Examinations'!$A$2:$A$2336,'Cleaned - Medical Examinations'!$F$2:$F$2336,0) -> No | H7: =_xlfn.XLOOKUP($A7,'Cleaned - Medical Examinations'!$A$2:$A$2336,'Cleaned - Medical Examinations'!$G$2:$G$2336,0) -> 0 | I7: =_xlfn.XLOOKUP($A7,'Cleaned - Medical Examinations'!$A$2:$A$2336,'Cleaned - Medical Examinations'!$H$2:$H$2336,0) -> Yes | J7: =_xlfn.XLOOKUP($A7,'Cleaned - Medical Examinations'!$A$2:$A$2336,'Cleaned - Medical Examinations'!$I$2:$I$2336,0) -> Obesity | K7: =IF(D7>=6.5,"Diabetic","Non-Diabetic") -> Diabetic | L7: =_xlfn.XLOOKUP($A7,'Cleaned - Hospitalisation Detai'!$A$2:$A$2344,'Cleaned - Hospitalisation Detai'!$J$2:$J$2344,0) -> 22862 | M7: =_xlfn.XLOOKUP($A7,'Cleaned - Hospitalisation Detai'!$A$2:$A$2344,'Cleaned - Hospitalisation Detai'!$F$2:$F$2344,0) -> 52590.83 | N7: =_xlfn.XLOOKUP($A7,'Cleaned - Hospitalisation Detai'!$A$2:$A$2344,'Cleaned - Hospitalisation Detai'!$G$2:$G$2344,0) -> tier - 1 | O7: =_xlfn.XLOOKUP($A7,'Cleaned - Hospitalisation Detai'!$A$2:$A$2344,'Cleaned - Hospitalisation Detai'!$H$2:$H$2344,0) -> tier - 3 | P7: =_xlfn.XLOOKUP($A7,'Cleaned - Hospitalisation Detai'!$A$2:$A$2344,'Cleaned - Hospitalisation Detai'!$I$2:$I$2344,0) -> R1011 | Q7: =_xlfn.XLOOKUP($A7,'Cleaned - Hospitalisation Detai'!$A$2:$A$2344,'Cleaned - Hospitalisation Detai'!$K$2:$K$2344,0) -> 60
A8: Id7 | B8: =_xlfn.XLOOKUP(A8,'Cleaned - Customer Names '!$A$2:$A$2336,'Cleaned - Customer Names '!$C$2:$C$2336,0) -> Scott | C8: =_xlfn.XLOOKUP($A8,'Cleaned - Medical Examinations'!$A$2:$A$2336,'Cleaned - Medical Examinations'!$B$2:$B$2336,0) -> 36.4 | D8: =_xlfn.XLOOKUP($A8,'Cleaned - Medical Examinations'!$A$2:$A$2336,'Cleaned - Medical Examinations'!$C$2:$C$2336,0) -> 6.07 | E8: =_xlfn.XLOOKUP($A8,'Cleaned - Medical Examinations'!$A$2:$A$2336,'Cleaned - Medical Examinations'!$D$2:$D$2336,0) -> No | F8: =_xlfn.XLOOKUP($A8,'Cleaned - Medical Examinations'!$A$2:$A$2336,'Cleaned - Medical Examinations'!$E$2:$E$2336,0) -> No | G8: =_xlfn.XLOOKUP($A8,'Cleaned - Medical Examinations'!$A$2:$A$2336,'Cleaned - Medical Examinations'!$F$2:$F$2336,0) -> No | H8: =_xlfn.XLOOKUP($A8,'Cleaned - Medical Examinations'!$A$2:$A$2336,'Cleaned - Medical Examinations'!$G$2:$G$2336,0) -> 0 | I8: =_xlfn.XLOOKUP($A8,'Cleaned - Medical Examinations'!$A$2:$A$2336,'Cleaned - Medical Examinations'!$H$2:$H$2336,0) -> Yes | J8: =_xlfn.XLOOKUP($A8,'Cleaned - Medical Examinations'!$A$2:$A$2336,'Cleaned - Medical Examinations'!$I$2:$I$2336,0) -> Obesity | K8: =IF(D8>=6.5,"Diabetic","Non-Diabetic") -> Non-Diabetic | L8: =_xlfn.XLOOKUP($A8,'Cleaned - Hospitalisation Detai'!$A$2:$A$2344,'Cleaned - Hospitalisation Detai'!$J$2:$J$2344,0) -> 34634 | M8: =_xlfn.XLOOKUP($A8,'Cleaned - Hospitalisation Detai'!$A$2:$A$2344,'Cleaned - Hospitalisation Detai'!$F$2:$F$2344,0) -> 51194.56 | N8: =_xlfn.XLOOKUP($A8,'Cleaned - Hospitalisation Detai'!$A$2:$A$2344,'Cleaned - Hospitalisation Detai'!$G$2:$G$2344,0) -> tier - 1 | O8: =_xlfn.XLOOKUP($A8,'Cleaned - Hospitalisation Detai'!$A$2:$A$2344,'Cleaned - Hospitalisation Detai'!$H$2:$H$2344,0) -> tier - 3 | P8: =_xlfn.XLOOKUP($A8,'Cleaned - Hospitalisation Detai'!$A$2:$A$2344,'Cleaned - Hospitalisation Detai'!$I$2:$I$2344,0) -> R1011 | Q8: =_xlfn.XLOOKUP($A8,'Cleaned - Hospitalisation Detai'!$A$2:$A$2344,'Cleaned - Hospitalisation Detai'!$K$2:$K$2344,0) -> 28
A9: Id8 | B9: =_xlfn.XLOOKUP(A9,'Cleaned - Customer Names '!$A$2:$A$2336,'Cleaned - Customer Names '!$C$2:$C$2336,0) -> Stephen | C9: =_xlfn.XLOOKUP($A9,'Cleaned - Medical Examinations'!$A$2:$A$2336,'Cleaned - Medical Examinations'!$B$2:$B$2336,0) -> 36.96 | D9: =_xlfn.XLOOKUP($A9,'Cleaned - Medical Examinations'!$A$2:$A$2336,'Cleaned - Medical Examinations'!$C$2:$C$2336,0) -> 7.93 | E9: =_xlfn.XLOOKUP($A9,'Cleaned - Medical Examinations'!$A$2:$A$2336,'Cleaned - Medical Examinations'!$D$2:$D$2336,0) -> No | F9: =_xlfn.XLOOKUP($A9,'Cleaned - Medical Examinations'!$A$2:$A$2336,'Cleaned - Medical Examinations'!$E$2:$E$2336,0) -> No | G9: =_xlfn.XLOOKUP($A9,'Cleaned - Medical Examinations'!$A$2:$A$2336,'Cleaned - Medical Examinations'!$F$2:$F$2336,0) -> No | H9: =_xlfn.XLOOKUP($A9,'Cleaned - Medical Examinations'!$A$2:$A$2336,'Cleaned - Medical Examinations'!$G$2:$G$2336,0) -> 3 | I9: =_xlfn.XLOOKUP($A9,'Cleaned - Medical Examinations'!$A$2:$A$2336,'Cleaned - Medical Examinations'!$H$2:$H$2336,0) -> Yes | J9: =_xlfn.XLOOKUP($A9,'Cleaned - Medical Examinations'!$A$2:$A$2336,'Cleaned - Medical Examinations'!$I$2:$I$2336,0) -> Obesity | K9: =IF(D9>=6.5,"Diabetic","Non-Diabetic") -> Diabetic | L9: =_xlfn.XLOOKUP($A9,'Cleaned - Hospitalisation Detai'!$A$2:$A$2344,'Cleaned - Hospitalisation Detai'!$J$2:$J$2344,0) -> 21363 | M9: =_xlfn.XLOOKUP($A9,'Cleaned - Hospitalisation Detai'!$A$2:$A$2344,'Cleaned - Hospitalisation Detai'!$F$2:$F$2344,0) -> 49577.66 | N9: =_xlfn.XLOOKUP($A9,'Cleaned - Hospitalisation Detai'!$A$2:$A$2344,'Cleaned - Hospitalisation Detai'!$G$2:$G$2344,0) -> tier - 2 | O9: =_xlfn.XLOOKUP($A9,'Cleaned - Hospitalisation Detai'!$A$2:$A$2344,'Cleaned - Hospitalisation Detai'!$H$2:$H$2344,0) -> tier - 2 | P9: =_xlfn.XLOOKUP($A9,'Cleaned - Hospitalisation Detai'!$A$2:$A$2344,'Cleaned - Hospitalisation Detai'!$I$2:$I$2344,0) -> R1013 | Q9: =_xlfn.XLOOKUP($A9,'Cleaned - Hospitalisation Detai'!$A$2:$A$2344,'Cleaned - Hospitalisation Detai'!$K$2:$K$2344,0) -> 64
A10: Id9 | B10: =_xlfn.XLOOKUP(A10,'Cleaned - Customer Names '!$A$2:$A$2336,'Cleaned - Customer Names '!$C$2:$C$2336,0) -> Patrick R. | C10: =_xlfn.XLOOKUP($A10,'Cleaned - Medical Examinations'!$A$2:$A$2336,'Cleaned - Medical Examinations'!$B$2:$B$2336,0) -> 41.14 | D10: =_xlfn.XLOOKUP($A10,'Cleaned - Medical Examinations'!$A$2:$A$2336,'Cleaned - Medical Examinations'!$C$2:$C$2336,0) -> 9.58 | E10: =_xlfn.XLOOKUP($A10,'Cleaned - Medical Examinations'!$A$2:$A$2336,'Cleaned - Medical Examinations'!$D$2:$D$2336,0) -> Yes | F10: =_xlfn.XLOOKUP($A10,'Cleaned - Medical Examinations'!$A$2:$A$2336,'Cleaned - Medical Examinations'!$E$2:$E$2336,0) -> No | G10: =_xlfn.XLOOKUP($A10,'Cleaned - Medical Examinations'!$A$2:$A$2336,'Cleaned - Medical Examinations'!$F$2:$F$2336,0) -> Yes | H10: =_xlfn.XLOOKUP($A10,'Cleaned - Medical Examinations'!$A$2:$A$2336,'Cleaned - Medical Examinations'!$G$2:$G$2336,0) -> 1 | I10: =_xlfn.XLOOKUP($A10,'Cleaned - Medical Examinations'!$A$2:$A$2336,'Cleaned - Medical Examinations'!$H$2:$H$2336,0) -> Yes | J10: =_xlfn.XLOOKUP($A10,'Cleaned - Medical Examinations'!$A$2:$A$2336,'Cleaned - Medical Examinations'!$I$2:$I$2336,0) -> Obesity | K10: =IF(D10>=6.5,"Diabetic","Non-Diabetic") -> Diabetic | L10: =_xlfn.XLOOKUP($A10,'Cleaned - Hospitalisation Detai'!$A$2:$A$2344,'Cleaned - Hospitalisation Detai'!$J$2:$J$2344,0) -> 23258 | M10: =_xlfn.XLOOKUP($A10,'Cleaned - Hospitalisation Detai'!$A$2:$A$2344,'Cleaned - Hospitalisation Detai'!$F$2:$F$2344,0) -> 48970.25 | N10: =_xlfn.XLOOKUP($A10,'Cleaned - Hospitalisation Detai'!$A$2:$A$2344,'Cleaned - Hospitalisation Detai'!$G$2:$G$2344,0) -> tier - 1 | O10: =_xlfn.XLOOKUP($A10,'Cleaned - Hospitalisation Detai'!$A$2:$A$2344,'Cleaned - Hospitalisation Detai'!$H$2:$H$2344,0) -> tier - 2 | P10: =_xlfn.XLOOKUP($A10,'Cleaned - Hospitalisation Detai'!$A$2:$A$2344,'Cleaned - Hospitalisation Detai'!$I$2:$I$2344,0) -> R1013 | Q10: =_xlfn.XLOOKUP($A10,'Cleaned - Hospitalisation Detai'!$A$2:$A$2344,'Cleaned - Hospitalisation Detai'!$K$2:$K$2344,0) -> 59
A11: Id10 | B11: =_xlfn.XLOOKUP(A11,'Cleaned - Customer Names '!$A$2:$A$2336,'Cleaned - Customer Names '!$C$2:$C$2336,0) -> Brooke N. | C11: =_xlfn.XLOOKUP($A11,'Cleaned - Medical Examinations'!$A$2:$A$2336,'Cleaned - Medical Examinations'!$B$2:$B$2336,0) -> 38.06 | D11: =_xlfn.XLOOKUP($A11,'Cleaned - Medical Examinations'!$A$2:$A$2336,'Cleaned - Medical Examinations'!$C$2:$C$2336,0) -> 10.79 | E11: =_xlfn.XLOOKUP($A11,'Cleaned - Medical Examinations'!$A$2:$A$2336,'Cleaned - Medical Examinations'!$D$2:$D$2336,0) -> No | F11: =_xlfn.XLOOKUP($A11,'Cleaned - Medical Examinations'!$A$2:$A$2336,'Cleaned - Medical Examinations'!$E$2:$E$2336,0) -> No | G11: =_xlfn.XLOOKUP($A11,'Cleaned - Medical Examinations'!$A$2:$A$2336,'Cleaned - Medical Examinations'!$F$2:$F$2336,0) -> No | H11: =_xlfn.XLOOKUP($A11,'Cleaned - Medical Examinations'!$A$2:$A$2336,'Cleaned - Medical Examinations'!$G$2:$G$2336,0) -> 0 | I11: =_xlfn.XLOOKUP($A11,'Cleaned - Medical Examinations'!$A$2:$A$2336,'Cleaned - Medical Examinations'!$H$2:$H$2336,0) -> Yes | J11: =_xlfn.XLOOKUP($A11,'Cleaned - Medical Examinations'!$A$2:$A$2336,'Cleaned - Medical Examinations'!$I$2:$I$2336,0) -> Obesity | K11: =IF(D11>=6.5,"Diabetic","Non-Diabetic") -> Diabetic | L11: =_xlfn.XLOOKUP($A11,'Cleaned - Hospitalisation Detai'!$A$2:$A$2344,'Cleaned - Hospitalisation Detai'!$J$2:$J$2344,0) -> 28853 | M11: =_xlfn.XLOOKUP($A11,'Cleaned - Hospitalisation Detai'!$A$2:$A$2344,'Cleaned - Hospitalisation Detai'!$F$2:$F$2344,0) -> 48885.14 | N11: =_xlfn.XLOOKUP($A11,'Cleaned - Hospitalisation Detai'!$A$2:$A$2344,'Cleaned - Hospitalisation Detai'!$G$2:$G$2344,0) -> tier - 1 | O11: =_xlfn.XLOOKUP($A11,'Cleaned - Hospitalisation Detai'!$A$2:$A$2344,'Cleaned - Hospitalisation Detai'!$H$2:$H$2344,0) -> tier - 2 | P11: =_xlfn.XLOOKUP($A11,'Cleaned - Hospitalisation Detai'!$A$2:$A$2344,'Cleaned - Hospitalisation Detai'!$I$2:$I$2344,0) -> R1013 | Q11: =_xlfn.XLOOKUP($A11,'Cleaned - Hospitalisation Detai'!$A$2:$A$2344,'Cleaned - Hospitalisation Detai'!$K$2:$K$2344,0) -> 44
A12: Id11 | B12: =_xlfn.XLOOKUP(A12,'Cleaned - Customer Names '!$A$2:$A$2336,'Cleaned - Customer Names '!$C$2:$C$2336,0) -> Paola Andrea | C12: =_xlfn.XLOOKUP($A12,'Cleaned - Medical Examinations'!$A$2:$A$2336,'Cleaned - Medical Examinations'!$B$2:$B$2336,0) -> 37.7 | D12: =_xlfn.XLOOKUP($A12,'Cleaned - Medical Examinations'!$A$2:$A$2336,'Cleaned - Medical Examinations'!$C$2:$C$2336,0) -> 5.96 | E12: =_xlfn.XLOOKUP($A12,'Cleaned - Medical Examinations'!$A$2:$A$2336,'Cleaned - Medical Examinations'!$D$2:$D$2336,0) -> Yes | F12: =_xlfn.XLOOKUP($A12,'Cleaned - Medical Examinations'!$A$2:$A$2336,'Cleaned - Medical Examinations'!$E$2:$E$2336,0) -> No | G12: =_xlfn.XLOOKUP($A12,'Cleaned - Medical Examinations'!$A$2:$A$2336,'Cleaned - Medical Examinations'!$F$2:$F$2336,0) -> No | H12: =_xlfn.XLOOKUP($A12,'Cleaned - Medical Examinations'!$A$2:$A$2336,'Cleaned - Medical Examinations'!$G$2:$G$2336,0) -> 2 | I12: =_xlfn.XLOOKUP($A12,'Cleaned - Medical Examinations'!$A$2:$A$2336,'Cleaned - Medical Examinations'!$H$2:$H$2336,0) -> Yes | J12: =_xlfn.XLOOKUP($A12,'Cleaned - Medical Examinations'!$A$2:$A$2336,'Cleaned - Medical Examinations'!$I$2:$I$2336,0) -> Obesity | K12: =IF(D12>=6.5,"Diabetic","Non-Diabetic") -> Non-Diabetic | L12: =_xlfn.XLOOKUP($A12,'Cleaned - Hospitalisation Detai'!$A$2:$A$2344,'Cleaned - Hospitalisation Detai'!$J$2:$J$2344,0) -> 21753 | M12: =_xlfn.XLOOKUP($A12,'Cleaned - Hospitalisation Detai'!$A$2:$A$2344,'Cleaned - Hospitalisation Detai'!$F$2:$F$2344,0) -> 48824.45 | N12: =_xlfn.XLOOKUP($A12,'Cleaned - Hospitalisation Detai'!$A$2:$A$2344,'Cleaned - Hospitalisation Detai'!$G$2:$G$2344,0) -> tier - 2 | O12: =_xlfn.XLOOKUP($A12,'Cleaned - Hospitalisation Detai'!$A$2:$A$2344,'Cleaned - Hospitalisation Detai'!$H$2:$H$2344,0) -> tier - 1 | P12: =_xlfn.XLOOKUP($A12,'Cleaned - Hospitalisation Detai'!$A$2:$A$2344,'Cleaned - Hospitalisation Detai'!$I$2:$I$2344,0) -> R1011 | Q12: =_xlfn.XLOOKUP($A12,'Cleaned - Hospitalisation Detai'!$A$2:$A$2344,'Cleaned - Hospitalisation Detai'!$K$2:$K$2344,0) -> 63
A13: Id12 | B13: =_xlfn.XLOOKUP(A13,'Cleaned - Customer Names '!$A$2:$A$2336,'Cleaned - Customer Names '!$C$2:$C$2336,0) -> David | C13: =_xlfn.XLOOKUP($A13,'Cleaned - Medical Examinations'!$A$2:$A$2336,'Cleaned - Medical Examinations'!$B$2:$B$2336,0) -> 42.13 | D13: =_xlfn.XLOOKUP($A13,'Cleaned - Medical Examinations'!$A$2:$A$2336,'Cleaned - Medical Examinations'!$C$2:$C$2336,0) -> 11.9 | E13: =_xlfn.XLOOKUP($A13,'Cleaned - Medical Examinations'!$A$2:$A$2336,'Cleaned - Medical Examinations'!$D$2:$D$2336,0) -> No | F13: =_xlfn.XLOOKUP($A13,'Cleaned - Medical Examinations'!$A$2:$A$2336,'Cleaned - Medical Examinations'!$E$2:$E$2336,0) -> No | G13: =_xlfn.XLOOKUP($A13,'Cleaned - Medical Examinations'!$A$2:$A$2336,'Cleaned - Medical Examinations'!$F$2:$F$2336,0) -> No | H13: =_xlfn.XLOOKUP($A13,'Cleaned - Medical Examinations'!$A$2:$A$2336,'Cleaned - Medical Examinations'!$G$2:$G$2336,0) -> 0 | I13: =_xlfn.XLOOKUP($A13,'Cleaned - Medical Examinations'!$A$2:$A$2336,'Cleaned - Medical Examinations'!$H$2:$H$2336,0) -> Yes | J13: =_xlfn.XLOOKUP($A13,'Cleaned - Medical Examinations'!$A$2:$A$2336,'Cleaned - Medical Examinations'!$I$2:$I$2336,0) -> Obesity | K13: =IF(D13>=6.5,"Diabetic","Non-Diabetic") -> Diabetic | L13: =_xlfn.XLOOKUP($A13,'Cleaned - Hospitalisation Detai'!$A$2:$A$2344,'Cleaned - Hospitalisation Detai'!$J$2:$J$2344,0) -> 24042 | M13: =_xlfn.XLOOKUP($A13,'Cleaned - Hospitalisation Detai'!$A$2:$A$2344,'Cleaned - Hospitalisation Detai'!$F$2:$F$2344,0) -> 48675.52 | N13: =_xlfn.XLOOKUP($A13,'Cleaned - Hospitalisation Detai'!$A$2:$A$2344,'Cleaned - Hospitalisation Detai'!$G$2:$G$2344,0) -> tier - 1 | O13: =_xlfn.XLOOKUP($A13,'Cleaned - Hospitalisation Detai'!$A$2:$A$2344,'Cleaned - Hospitalisation Detai'!$H$2:$H$2344,0) -> tier - 2 | P13: =_xlfn.XLOOKUP($A13,'Cleaned - Hospitalisation Detai'!$A$2:$A$2344,'Cleaned - Hospitalisation Detai'!$I$2:$I$2344,0) -> R1013 | Q13: =_xlfn.XLOOKUP($A13,'Cleaned - Hospitalisation Detai'!$A$2:$A$2344,'Cleaned - Hospitalisation Detai'!$K$2:$K$2344,0) -> 57
... A2336: Id2335 | B2336: =_xlfn.XLOOKUP(A2336,'Cleaned - Customer Names '!$A$2:$A$2336,'Cleaned - Customer Names '!$C$2:$C$2336,0) -> Aaron K | C2336: =_xlfn.XLOOKUP($A2336,'Cleaned - Medical Examinations'!$A$2:$A$2336,'Cleaned - Medical Examinations'!$B$2:$B$2336,0) -> 17.58 | D2336: =_xlfn.XLOOKUP($A2336,'Cleaned - Medical Examinations'!$A$2:$A$2336,'Cleaned - Medical Examinations'!$C$2:$C$2336,0) -> 4.51 | E2336: =_xlfn.XLOOKUP($A2336,'Cleaned - Medical Examinations'!$A$2:$A$2336,'Cleaned - Medical Examinations'!$D$2:$D$2336,0) -> No | F2336: =_xlfn.XLOOKUP($A2336,'Cleaned - Medical Examinations'!$A$2:$A$2336,'Cleaned - Medical Examinations'!$E$2:$E$2336,0) -> No | G2336: =_xlfn.XLOOKUP($A2336,'Cleaned - Medical Examinations'!$A$2:$A$2336,'Cleaned - Medical Examinations'!$F$2:$F$2336,0) -> No | H2336: =_xlfn.XLOOKUP($A2336,'Cleaned - Medical Examinations'!$A$2:$A$2336,'Cleaned - Medical Examinations'!$G$2:$G$2336,0) -> 1 | I2336: =_xlfn.XLOOKUP($A2336,'Cleaned - Medical Examinations'!$A$2:$A$2336,'Cleaned - Medical Examinations'!$H$2:$H$2336,0) -> No | J2336: =_xlfn.XLOOKUP($A2336,'Cleaned - Medical Examinations'!$A$2:$A$2336,'Cleaned - Medical Examinations'!$I$2:$I$2336,0) -> Underweight | K2336: =IF(D2336>=6.5,"Diabetic","Non-Diabetic") -> Non-Diabetic | L2336: =_xlfn.XLOOKUP($A2336,'Cleaned - Hospitalisation Detai'!$A$2:$A$2344,'Cleaned - Hospitalisation Detai'!$J$2:$J$2344,0) -> 33794 | M2336: =_xlfn.XLOOKUP($A2336,'Cleaned - Hospitalisation Detai'!$A$2:$A$2344,'Cleaned - Hospitalisation Detai'!$F$2:$F$2344,0) -> 563.84 | N2336: =_xlfn.XLOOKUP($A2336,'Cleaned - Hospitalisation Detai'!$A$2:$A$2344,'Cleaned - Hospitalisation Detai'!$G$2:$G$2344,0) -> tier - 2 | O2336: =_xlfn.XLOOKUP($A2336,'Cleaned - Hospitalisation Detai'!$A$2:$A$2344,'Cleaned - Hospitalisation Detai'!$H$2:$H$2344,0) -> tier - 3 | P2336: =_xlfn.XLOOKUP($A2336,'Cleaned - Hospitalisation Detai'!$A$2:$A$2344,'Cleaned - Hospitalisation Detai'!$I$2:$I$2344,0) -> R1013 | Q2336: =_xlfn.XLOOKUP($A2336,'Cleaned - Hospitalisation Detai'!$A$2:$A$2344,'Cleaned - Hospitalisation Detai'!$K$2:$K$2344,0) -> 30
A2337: =COUNTA(A2:A2336) -> 2335 | B2337: =COUNTA(B2:B2336) -> 2335 | C2337: =AVERAGE(C2:C2336) -> 30.972649 | D2337: =AVERAGE(D2:D2336) -> 6.5789979 | M2337: =SUM(M2:M2336) -> 31592359 | Q2337: =AVERAGE(Q2:Q2336) -> 39.228694
B2338: Total Customer Count | C2338: Average BMI | D2338: Average HBA1C | M2338: Total Cost | Q2338: Average Age

Sheet Pivot Table
A3: Row Labels | B3: Count of Cancer History
A4: No | B4: 307
A5: Yes | B5: 84
A6: Grand Total | B6: 391
L9: Insights
L10: 1) Smokers have a slightly higher history of cancer (21.5%) compared to non-smokers (20.8%) in this dataset. However, the difference between the two groups is very small (0.7 percentage points), suggesting that cancer history is nearly similar among smokers and non-smokers in this datser.
L11: 2) The obesity category records the highest average healthcare charges among all weight status groups.
L13: Note. Since a pie chart supports only one categorical variable, a pie chart was created for Smoker vs. Non-Smoker, and a slicer was added to filter and analyze cancer history for each group.
A17: Charges Vs Weight Status
A18: Row Labels | B18: Count of Weight Status
A19: Normal Weight | B19: 68
A20: Obesity | B20: 199
A21: Overweight | B21: 94
A22: Underweight | B22: 30
A23: Grand Total | B23: 391
A30: DIAbetic Status | B30: Count of Diabetes Status
A31: Diabetic | B31: 48
A32: Non-Diabetic | B32: 343
A33: Grand Total | B33: 391
A42: Row Labels | B42: Count of Weight Status
A43: Normal Weight | B43: 68
A44: Obesity | B44: 199
A45: Overweight | B45: 94
A46: Underweight | B46: 30
A47: Grand Total | B47: 391

Sheet Dashboard
A1: Healthcare Dashboard

Sheet Observation
A1: Observations
A2: Data Cleaning
A3: 1) There is no missing value marked with ? In medical examinations. And 15 missing values marked with ? In hospitalisation details. 6 missing values in customer ID, 2 missing value in Year, 3 missing value in month, 1 missing value in hospital tier,1 missing value in city tier and 2 in state ID
A4: 2) Missing values in Month has been replaced with Sep and year has been replaced with 1983 because the average is 1982.842. Average calculated in cell
A5: 3) most frequently occurring values in the ‘smoker’, 'hospital tier', and 'city tier'columns has been determined using combination of index match and mode, we can also use Countif funcation as we have max 3 unique datas in these column also power query is the one of the best methos to find mode. The values are Smoker - No, Hospital tier - Tier 2, City Tier - Tier 3
A6: 4) 'State ID' values are missingvalues are replaced with 'Unknown'
A8: Data Transformation
A9: 1) Customer names splitted into 3 meaningfull columns: ‘Title’,‘First Name’, and ‘Last Name’.
A10: 2) "NumberOfMajorSurgeries" column in the "Medical Examinations" table convertedd tonumerical data by replacing non-numeric characters with meaningful numerical value 0.
A11: 3) inconsistencies in the 'Heart Issues' and 'Smoker' columns has been fixed using Filter option
A12: 4)“Weight Status” column created and data fetched as given.
A13: 5) Date of birth column created using =Date Function
... A15: 7) Charges column formatted to currency
A16: AI-Driven Data Exploration | B16: Analysis & Visualization:
A17: Activity 1: Data Preparation
A18: ID1)“Healthcare”, sheet created using XLOOKUP function with required columns. 2 customer ID(ID2444,ID3444) not found in Customer names and Medical examinations sheet.
A19: Activity 2: Manual Dashboard Build
A20: Insights
A21: 1) Smokers have a slightly higher history of cancer (21.5%) compared to non-smokers (20.8%) in this dataset. However, the difference between the two groups is very small (0.7 percentage points), suggesting that cancer history is nearly similar among smokers and non-smokers in this datser.
A22: 2) The obesity category records the highest average healthcare charges among all weight status groups.
A23: Note. Since a pie chart supports only one categorical variable, a pie chart was created for Smoker vs. Non-Smoker, and a slicer was added to filter and analyze cancer history for each group.
A24: Activity 3: AI-Powered Summary Statistics & Visualization
A25: 1)Combined dataset named “New -Health Care” Highlighted
A26: 2) Total customers count,Total healthcare costs,Average medical metrics has been calculated using quick analysis in row 2337. Total hospitalisation count is calculated in Cleaned hospitalization sheet.
A27: 3) Quick Analysis → Recommended Charts created in Pivot table sheet has been created
A28: Activity 4: Dashboard Creation
... A38: 6)The dashboard enables comparison of healthcare costs across different weight categories, helping identify high-cost patient groups.

Sheet Customer Names
A1: Customer ID | B1: name
A2: Id1 | B2: Hawks, Ms. Kelly
A3: Id2 | B3: Lehner, Mr. Matthew D
A4: Id3 | B4: Lu, Mr. Phil
A5: Id4 | B5: Osborne, Ms. Kelsey
A6: Id5 | B6: Kadala, Ms. Kristyn
A7: Id6 | B7: Baker, Mr. Russell B.
A8: Id7 | B8: Macpherson, Mr. Scott
A9: Id8 | B9: Hallman, Mr. Stephen
A10: Id9 | B10: Moran, Mr. Patrick R.
A11: Id10 | B11: Benner, Ms. Brooke N.
A12: Id11 | B12: Fierro Vargas, Ms. Paola Andrea
... A2336: Id2335 | B2336: German, Mr. Aaron K

Sheet Medical Examinations
A1: Customer ID | B1: BMI | C1: HBA1C | D1: Heart Issues | E1: Any Transplants | F1: Cancer history | G1: NumberOfMajorSurgeries | H1: smoker
A2: Id1 | B2: 47.41 | C2: 7.47 | D2: No | E2: No | F2: No | G2: No major surgery | H2: yes
A3: Id2 | B3: 30.36 | C3: 5.77 | D3: No | E3: No | F3: No | G3: No major surgery | H3: yes
A4: Id3 | B4: 34.485 | C4: 11.87 | D4: yes | E4: No | F4: No | G4: 2 | H4: yes
A5: Id4 | B5: 38.095 | C5: 6.05 | D5: No | E5: No | F5: No | G5: No major surgery | H5: yes
A6: Id5 | B6: 35.53 | C6: 5.45 | D6: No | E6: No | F6: No | G6: No major surgery | H6: yes
A7: Id6 | B7: 32.8 | C7: 6.59 | D7: No | E7: No | F7: No | G7: No major surgery | H7: yes
A8: Id7 | B8: 36.4 | C8: 6.07 | D8: No | E8: No | F8: No | G8: No major surgery | H8: yes
A9: Id8 | B9: 36.96 | C9: 7.93 | D9: No | E9: No | F9: No | G9: 3 | H9: yes
A10: Id9 | B10: 41.14 | C10: 9.58 | D10: yes | E10: No | F10: Yes | G10: 1 | H10: yes
A11: Id10 | B11: 38.06 | C11: 10.79 | D11: No | E11: No | F11: No | G11: No major surgery | H11: yes
A12: Id11 | B12: 37.7 | C12: 5.96 | D12: yes | E12: No | F12: No | G12: 2 | H12: yes
A13: Id12 | B13: 42.13 | C13: 11.9 | D13: No | E13: No | F13: No | G13: No major surgery | H13: yes
A14: Id13 | B14: 40.92 | C14: 8.41 | D14: No | E14: No | F14: No | G14: No major surgery | H14: yes
A15: Id14 | B15: 40.565 | C15: 7.02 | D15: No | E15: No | F15: No | G15: No major surgery | H15: yes
A16: Id15 | B16: 36.385 | C16: 7.59 | D16: yes | E16: No | F16: No | G16: 2 | H16: yes
A17: Id16 | B17: 39.9 | C17: 11.32 | D17: No | E17: No | F17: No | G17: No major surgery | H17: yes
A18: Id17 | B18: 33.8 | C18: 7.67 | D18: No | E18: No | F18: No | G18: 3 | H18: yes
A19: Id18 | B19: 36.765 | C19: 7.29 | D19: yes | E19: No | F19: Yes | G19: 1 | H19: yes
A20: Id19 | B20: 36.955 | C20: 4.72 | D20: yes | E20: No | F20: No | G20: 1 | H20: yes
A21: Id20 | B21: 42.9 | C21: 11.41 | D21: No | E21: No | F21: No | G21: No major surgery | H21: yes
A22: Id21 | B22: 36.3 | C22: 11.5 | D22: yes | E22: No | F22: No | G22: 2 | H22: yes
A23: Id22 | B23: 32.2 | C23: 6.22 | D23: yes | E23: No | F23: No | G23: 2 | H23: yes
A24: Id23 | B24: 31.3 | C24: 11.38 | D24: No | E24: No | F24: No | G24: 3 | H24: yes
A25: Id24 | B25: 41.8 | C25: 7.89 | D25: yes | E25: No | F25: No | G25: 2 | H25: yes
A26: Id25 | B26: 35.09 | C26: 4.38 | D26: yes | E26: No | F26: No | G26: 2 | H26: yes
A27: Id26 | B27: 33.88 | C27: 7.01 | D27: No | E27: No | F27: No | G27: 3 | H27: yes
A28: Id27 | B28: 30.875 | C28: 11.88 | D28: No | E28: No | F28: No | G28: No major surgery | H28: yes
A29: Id28 | B29: 36.86 | C29: 5.19 | D29: yes | E29: No | F29: Yes | G29: 1 | H29: yes
A30: Id29 | B30: 35.86 | C30: 6.74 | D30: yes | E30: No | F30: No | G30: 2 | H30: yes
A31: Id30 | B31: 37.05 | C31: 8.44 | D31: No | E31: No | F31: No | G31: No major surgery | H31: yes
A32: Id31 | B32: 43.89 | C32: 8.71 | D32: No | E32: No | F32: No | G32: No major surgery | H32: yes
A33: Id32 | B33: 42.35 | C33: 5.08 | D33: yes | E33: No | F33: No | G33: No major surgery | H33: yes
A34: Id33 | B34: 31.35 | C34: 6.86 | D34: No | E34: No | F34: No | G34: No major surgery | H34: yes
A35: Id34 | B35: 47.6 | C35: 5.95 | D35: yes | E35: No | F35: No | G35: No major surgery | H35: yes
A36: Id35 | B36: 46.2 | C36: 6.09 | D36: No | E36: No | F36: Yes | G36: 1 | H36: yes
A37: Id36 | B37: 32.015 | C37: 11.75 | D37: No | E37: No | F37: No | G37: No major surgery | H37: yes
A38: Id37 | B38: 40.565 | C38: 7.37 | D38: No | E38: No | F38: No | G38: No major surgery | H38: yes
A39: Id38 | B39: 32.45 | C39: 11.91 | D39: No | E39: No | F39: No | G39: No major surgery | H39: yes
A40: Id39 | B40: 34.96 | C40: 6.52 | D40: No | E40: No | F40: No | G40: No major surgery | H40: yes
A41: Id40 | B41: 35.5 | C41: 5.14 | D41: No | E41: No | F41: Yes | G41: 1 | H41: yes
A42: Id41 | B42: 52.58 | C42: 4.19 | D42: No | E42: yes | F42: No | G42: 1 | H42: yes
A43: Id42 | B43: 35.2 | C43: 11.68 | D43: yes | E43: No | F43: No | G43: No major surgery | H43: yes
A44: Id43 | B44: 38.06 | C44: 6.98 | D44: No | E44: No | F44: No | G44: No major surgery | H44: yes
A45: Id44 | B45: 34.21 | C45: 8.34 | D45: No | E45: No | F45: No | G45: No major surgery | H45: yes
A46: Id45 | B46: 38.94 | C46: 8.49 | D46: yes | E46: No | F46: No | G46: 1 | H46: yes
A47: Id46 | B47: 30.21 | C47: 5.34 | D47: yes | E47: No | F47: No | G47: 1 | H47: yes
A48: Id47 | B48: 33.63 | C48: 4.43 | D48: yes | E48: No | F48: No | G48: 2 | H48: yes
A49: Id48 | B49: 40.37 | C49: 4.47 | D49: No | E49: No | F49: No | G49: No major surgery | H49: yes
A50: Id49 | B50: 53.09 | C50: 4.82 | D50: yes | E50: No | F50: No | G50: 2 | H50: yes
A51: Id50 | B51: 31.79 | C51: 5.51 | D51: yes | E51: No | F51: No | G51: 2 | H51: yes
A52: Id51 | B52: 41.895 | C52: 10.87 | D52: yes | E52: No | F52: No | G52: 1 | H52: yes
A53: Id52 | B53: 31.16 | C53: 9.34 | D53: No | E53: No | F53: No | G53: No major surgery | H53: yes
A54: Id53 | B54: 34.105 | C54: 5.03 | D54: yes | E54: No | F54: Yes | G54: 1 | H54: yes
A55: Id54 | B55: 51.93 | C55: 11.05 | D55: No | E55: No | F55: No | G55: No major surgery | H55: yes
A56: Id55 | B56: 38.95 | C56: 11.95 | D56: No | E56: No | F56: No | G56: No major surgery | H56: yes
A57: Id56 | B57: 36.63 | C57: 7.72 | D57: yes | E57: No | F57: No | G57: 1 | H57: yes
A58: Id57 | B58: 34.2 | C58: 5.75 | D58: No | E58: No | F58: No | G58: 2 | H58: yes
A59: Id58 | B59: 50.63 | C59: 11.89 | D59: No | E59: No | F59: No | G59: No major surgery | H59: yes
A60: Id59 | B60: 36.48 | C60: 6.2 | D60: No | E60: No | F60: No | G60: No major surgery | H60: yes
A61: Id60 | B61: 54.82 | C61: 10.61 | D61: No | E61: No | F61: No | G61: No major surgery | H61: yes
A62: Id61 | B62: 38.06 | C62: 6.04 | D62: No | E62: No | F62: Yes | G62: 1 | H62: yes
A63: Id62 | B63: 51.48 | C63: 9.33 | D63: yes | E63: No | F63: No | G63: No major surgery | H63: yes
A64: Id63 | B64: 52.06 | C64: 11.47 | D64: No | E64: No | F64: No | G64: No major surgery | H64: yes
A65: Id64 | B65: 30.685 | C65: 7.02 | D65: yes | E65: No | F65: No | G65: No major surgery | H65: yes
A66: Id65 | B66: 36.08 | C66: 8.8 | D66: yes | E66: No | F66: No | G66: 1 | H66: yes
A67: Id66 | B67: 54.99 | C67: 8.68 | D67: No | E67: No | F67: No | G67: 2 | H67: yes
A68: Id67 | B68: 35.97 | C68: 6.12 | D68: No | E68: No | F68: Yes | G68: 1 | H68: yes
A69: Id68 | B69: 45.54 | C69: 5.4 | D69: yes | E69: No | F69: Yes | G69: 1 | H69: yes
A70: Id69 | B70: 35.53 | C70: 4.36 | D70: yes | E70: No | F70: No | G70: No major surgery | H70: yes
A71: Id70 | B71: 30.8 | C71: 9.77 | D71: No | E71: No | F71: No | G71: No major surgery | H71: yes
A72: Id71 | B72: 38.39 | C72: 4.25 | D72: No | E72: No | F72: No | G72: 1 | H72: yes
A73: Id72 | B73: 32.3 | C73: 4.76 | D73: No | E73: No | F73: No | G73: 2 | H73: yes
A74: Id73 | B74: 48.8 | C74: 6.22 | D74: yes | E74: No | F74: No | G74: 2 | H74: yes
A75: Id74 | B75: 45.5 | C75: 7.96 | D75: No | E75: No | F75: No | G75: No major surgery | H75: yes
A76: Id75 | B76: 53.61 | C76: 10.92 | D76: yes | E76: No | F76: No | G76: 1 | H76: yes
A77: Id76 | B77: 36.19 | C77: 11.51 | D77: yes | E77: No | F77: No | G77: 1 | H77: yes
A78: Id77 | B78: 34.6 | C78: 5.99 | D78: yes | E78: No | F78: No | G78: No major surgery | H78: yes
A79: Id78 | B79: 54.12 | C79: 11.57 | D79: No | E79: No | F79: No | G79: No major surgery | H79: yes
A80: Id79 | B80: 48.82 | C80: 6.67 | D80: yes | E80: No | F80: No | G80: No major surgery | H80: yes
A81: Id80 | B81: 51.01 | C81: 9.2 | D81: No | E81: No | F81: No | G81: No major surgery | H81: yes
A82: Id81 | B82: 45.65 | C82: 5.11 | D82: yes | E82: No | F82: No | G82: 1 | H82: yes
A83: Id82 | B83: 52.9 | C83: 5.34 | D83: No | E83: No | F83: No | G83: No major surgery | H83: yes
A84: Id83 | B84: 45.41 | C84: 4.03 | D84: yes | E84: No | F84: No | G84: 1 | H84: yes
A85: Id84 | B85: 49.41 | C85: 4.23 | D85: yes | E85: No | F85: Yes | G85: 1 | H85: yes
A86: Id85 | B86: 31.825 | C86: 4.06 | D86: No | E86: No | F86: No | G86: 2 | H86: yes
A87: Id86 | B87: 51.28 | C87: 4.68 | D87: No | E87: No | F87: No | G87: 2 | H87: yes
A88: Id87 | B88: 34.96 | C88: 4.34 | D88: No | E88: No | F88: Yes | G88: 1 | H88: yes
A89: Id88 | B89: 33.11 | C89: 10.51 | D89: No | E89: No | F89: No | G89: No major surgery | H89: yes
A90: Id89 | B90: 54.74 | C90: 5.84 | D90: yes | E90: No | F90: Yes | G90: 1 | H90: yes
A91: Id90 | B91: 32.56 | C91: 5.41 | D91: No | E91: No | F91: Yes | G91: 1 | H91: yes
A92: Id91 | B92: 39.05 | C92: 6.06 | D92: No | E92: No | F92: No | G92: 1 | H92: yes
A93: Id92 | B93: 42.75 | C93: 4.22 | D93: No | E93: No | F93: No | G93: No major surgery | H93: yes
A94: Id93 | B94: 50.58 | C94: 5.12 | D94: No | E94: No | F94: No | G94: 2 | H94: yes
A95: Id94 | B95: 30.495 | C95: 4.57 | D95: yes | E95: No | F95: No | G95: No major surgery | H95: yes
A96: Id95 | B96: 48.31 | C96: 9.58 | D96: yes | E96: No | F96: No | G96: 2 | H96: yes
A97: Id96 | B97: 48.99 | C97: 9.78 | D97: yes | E97: No | F97: No | G97: 1 | H97: yes
A98: Id97 | B98: 38.39 | C98: 4.11 | D98: yes | E98: No | F98: No | G98: No major surgery | H98: yes
A99: Id98 | B99: 44.34 | C99: 4.02 | D99: yes | E99: No | F99: No | G99: 2 | H99: yes
A100: Id99 | B100: 41.51 | C100: 6.92 | D100: No | E100: No | F100: No | G100: No major surgery | H100: yes
...

Sheet Hospitalisation Details
A1: Customer ID | B1: year | C1: month | D1: date | E1: children | F1: charges | G1: Hospital tier | H1: City tier | I1: State ID
A2: Id2335 | B2: 1992 | C2: Jul | D2: 9 | E2: 0 | F2: 563.84 | G2: tier - 2 | H2: tier - 3 | I2: R1013
A3: Id2334 | B3: 1992 | C3: Nov | D3: 30 | E3: 0 | F3: 570.62 | G3: tier - 2 | H3: tier - 1 | I3: R1013
A4: Id2333 | B4: 1993 | C4: Jun | D4: 30 | E4: 0 | F4: 600 | G4: tier - 2 | H4: tier - 1 | I4: R1013
A5: Id2332 | B5: 1992 | C5: Sep | D5: 13 | E5: 0 | F5: 604.54 | G5: tier - 3 | H5: tier - 3 | I5: R1013
A6: Id2331 | B6: 1998 | C6: Jul | D6: 27 | E6: 0 | F6: 637.26 | G6: tier - 3 | H6: tier - 3 | I6: R1013
A7: Id2330 | B7: 2001 | C7: Nov | D7: 20 | E7: 0 | F7: 646.14 | G7: tier - 3 | H7: tier - 3 | I7: R1012
A8: Id2329 | B8: 1993 | C8: Jun | D8: 1 | E8: 0 | F8: 650 | G8: tier - 3 | H8: tier - 3 | I8: R1013
A9: Id2328 | B9: 1995 | C9: Jul | D9: 4 | E9: 0 | F9: 650 | G9: tier - 3 | H9: tier - 3 | I9: R1013
A10: Id2327 | B10: 2002 | C10: Nov | D10: 29 | E10: 0 | F10: 668 | G10: tier - 3 | H10: tier - 2 | I10: R1012
A11: Id2326 | B11: 1997 | C11: Nov | D11: 9 | E11: 0 | F11: 670 | G11: tier - 3 | H11: tier - 3 | I11: R1013
A12: Id2325 | B12: 2001 | C12: Sep | D12: 12 | E12: 0 | F12: 687.54 | G12: tier - 3 | H12: tier - 2 | I12: R1013
A13: Id2324 | B13: 1999 | C13: Dec | D13: 26 | E13: 0 | F13: 700 | G13: ? | H13: tier - 3 | I13: R1013
... A1050: Id1290 | B1050: 1977 | C1050: Jul | D1050: 26 | E1050: 2 | F1050: 8527.53 | G1050: tier - 2 | H1050: tier - 2 | I1050: R1013
A1051: Id1289 | B1051: ? | C1051: Jul | D1051: 24 | E1051: 0 | F1051: 8534.67 | G1051: tier - 2 | H1051: tier - 3 | I1051: R1024
A1052: Id1288 | B1052: 1981 | C1052: Dec | D1052: 27 | E1052: 3 | F1052: 8538.29 | G1052: tier - 2 | H1052: tier - 3 | I1052: R1024
A1053: Id1287 | B1053: 1975 | C1053: Nov | D1053: 6 | E1053: 1 | F1053: 8539.67 | G1053: tier - 2 | H1053: tier - 3 | I1053: R1011
A1054: Id1286 | B1054: ? | C1054: Dec | D1054: 12 | E1054: 1 | F1054: 8547.69 | G1054: tier - 2 | H1054: tier - 1 | I1054: R1013
A1055: Id1285 | B1055: 1975 | C1055: Aug | D1055: 6 | E1055: 1 | F1055: 8551.35 | G1055: tier - 2 | H1055: tier - 2 | I1055: R1011
A1056: Id1284 | B1056: 1975 | C1056: Aug | D1056: 21 | E1056: 1 | F1056: 8556.91 | G1056: tier - 2 | H1056: tier - 1 | I1056: R1011
A1057: Id1283 | B1057: 1988 | C1057: Sep | D1057: 21 | E1057: 3 | F1057: 8567.25 | G1057: tier - 2 | H1057: tier - 1 | I1057: R1012
A1058: Id1282 | B1058: 1975 | C1058: Sep | D1058: 26 | E1058: 1 | F1058: 8569.86 | G1058: tier - 2 | H1058: tier - 3 | I1058: R1013
A1059: Id1281 | B1059: 1982 | C1059: Dec | D1059: 6 | E1059: 3 | F1059: 8572.04 | G1059: tier - 2 | H1059: tier - 2 | I1059: R1021
A1060: Id1280 | B1060: 1987 | C1060: Nov | D1060: 11 | E1060: 3 | F1060: 8573.3 | G1060: tier - 2 | H1060: tier - 2 | I1060: R1021
A1061: Id1279 | B1061: 1983 | C1061: Dec | D1061: 30 | E1061: 5 | F1061: 8582.3 | G1061: tier - 2 | H1061: tier - 1 | I1061: R1013
A1062: Id1278 | B1062: 1983 | C1062: Jul | D1062: 25 | E1062: 5 | F1062: 8596.83 | G1062: tier - 2 | H1062: tier - 3 | I1062: R1013
A1063: Id1277 | B1063: 1973 | C1063: Jul | D1063: 11 | E1063: 0 | F1063: 8601.33 | G1063: tier - 2 | H1063: tier - 1 | I1063: R1013
A1064: Id1276 | B1064: 1977 | C1064: Sep | D1064: 24 | E1064: 2 | F1064: 8603.82 | G1064: tier - 2 | H1064: tier - 1 | I1064: R1019
A1065: Id1275 | B1065: 1977 | C1065: Nov | D1065: 12 | E1065: 2 | F1065: 8604.48 | G1065: tier - 3 | H1065: tier - 2 | I1065: R1016
A1066: Id1274 | B1066: 1977 | C1066: Oct | D1066: 15 | E1066: 3 | F1066: 8605.36 | G1066: tier - 2 | H1066: tier - 2 | I1066: R1013
... A2344: Id1 | B2344: 1968 | C2344: Oct | D2344: 12 | E2344: 0 | F2344: 63770.43 | G2344: tier - 1 | H2344: tier - 3 | I2344: R1013
